{"18001":[{"city":"BOURGES CEDEX","zipcode_valid":"18000","city_valid":"BOURGES"}],"18002":[{"city":"BOURGES CEDEX","zipcode_valid":"18000","city_valid":"BOURGES"}],"18003":[{"city":"BOURGES CEDEX","zipcode_valid":"18000","city_valid":"BOURGES"}],"18004":[{"city":"BOURGES CEDEX","zipcode_valid":"18000","city_valid":"BOURGES"}],"18005":[{"city":"BOURGES CEDEX","zipcode_valid":"18000","city_valid":"BOURGES"}],"18006":[{"city":"BOURGES CEDEX","zipcode_valid":"18000","city_valid":"BOURGES"}],"18007":[{"city":"BOURGES CEDEX","zipcode_valid":"18000","city_valid":"BOURGES"}],"18008":[{"city":"BOURGES CEDEX","zipcode_valid":"18000","city_valid":"BOURGES"}],"18009":[{"city":"BOURGES CEDEX","zipcode_valid":"18000","city_valid":"BOURGES"}],"18010":[{"city":"BOURGES CEDEX","zipcode_valid":"18000","city_valid":"BOURGES"}],"18011":[{"city":"BOURGES CEDEX","zipcode_valid":"18000","city_valid":"BOURGES"}],"18012":[{"city":"BOURGES CEDEX","zipcode_valid":"18000","city_valid":"BOURGES"}],"18013":[{"city":"BOURGES CEDEX","zipcode_valid":"18000","city_valid":"BOURGES"}],"18014":[{"city":"BOURGES CEDEX","zipcode_valid":"18000","city_valid":"BOURGES"}],"18015":[{"city":"BOURGES CEDEX","zipcode_valid":"18000","city_valid":"BOURGES"}],"18016":[{"city":"BOURGES CEDEX","zipcode_valid":"18000","city_valid":"BOURGES"}],"18017":[{"city":"BOURGES CEDEX","zipcode_valid":"18000","city_valid":"BOURGES"}],"18018":[{"city":"BOURGES CEDEX","zipcode_valid":"18000","city_valid":"BOURGES"}],"18019":[{"city":"BOURGES CEDEX","zipcode_valid":"18000","city_valid":"BOURGES"}],"18020":[{"city":"BOURGES CEDEX","zipcode_valid":"18000","city_valid":"BOURGES"}],"18021":[{"city":"BOURGES CEDEX","zipcode_valid":"18000","city_valid":"BOURGES"}],"18022":[{"city":"BOURGES CEDEX","zipcode_valid":"18000","city_valid":"BOURGES"}],"18023":[{"city":"BOURGES CEDEX","zipcode_valid":"18000","city_valid":"BOURGES"}],"18024":[{"city":"BOURGES CEDEX","zipcode_valid":"18000","city_valid":"BOURGES"}],"18025":[{"city":"BOURGES CEDEX","zipcode_valid":"18000","city_valid":"BOURGES"}],"18026":[{"city":"BOURGES CEDEX","zipcode_valid":"18000","city_valid":"BOURGES"}],"18027":[{"city":"BOURGES CEDEX","zipcode_valid":"18000","city_valid":"BOURGES"}],"18028":[{"city":"BOURGES CEDEX","zipcode_valid":"18000","city_valid":"BOURGES"}],"18029":[{"city":"BOURGES CEDEX","zipcode_valid":"18000","city_valid":"BOURGES"}],"18030":[{"city":"BOURGES CEDEX 9","zipcode_valid":"18000","city_valid":"BOURGES"}],"18031":[{"city":"BOURGES CEDEX 9","zipcode_valid":"18000","city_valid":"BOURGES"}],"18032":[{"city":"BOURGES CEDEX 9","zipcode_valid":"18000","city_valid":"BOURGES"}],"18033":[{"city":"BOURGES CEDEX 9","zipcode_valid":"18000","city_valid":"BOURGES"}],"18034":[{"city":"BOURGES CEDEX 9","zipcode_valid":"18000","city_valid":"BOURGES"}],"18035":[{"city":"BOURGES CEDEX","zipcode_valid":"18000","city_valid":"BOURGES"}],"18036":[{"city":"BOURGES CEDEX","zipcode_valid":"18000","city_valid":"BOURGES"}],"18037":[{"city":"BOURGES CEDEX","zipcode_valid":"18000","city_valid":"BOURGES"}],"18038":[{"city":"BOURGES CEDEX","zipcode_valid":"18000","city_valid":"BOURGES"}],"18039":[{"city":"BOURGES CEDEX","zipcode_valid":"18000","city_valid":"BOURGES"}],"18040":[{"city":"BOURGES CEDEX","zipcode_valid":"18000","city_valid":"BOURGES"}],"18101":[{"city":"VIERZON CEDEX","zipcode_valid":"18100","city_valid":"VIERZON"}],"18102":[{"city":"VIERZON CEDEX","zipcode_valid":"18100","city_valid":"VIERZON"}],"18103":[{"city":"VIERZON CEDEX","zipcode_valid":"18100","city_valid":"VIERZON"}],"18104":[{"city":"VIERZON CEDEX","zipcode_valid":"18100","city_valid":"VIERZON"}],"18105":[{"city":"VIERZON CEDEX","zipcode_valid":"18100","city_valid":"VIERZON"}],"18106":[{"city":"VIERZON CEDEX","zipcode_valid":"18100","city_valid":"VIERZON"}],"18107":[{"city":"VIERZON CEDEX","zipcode_valid":"18100","city_valid":"VIERZON"}],"18108":[{"city":"VIERZON CEDEX","zipcode_valid":"18100","city_valid":"VIERZON"}],"18109":[{"city":"VIERZON CEDEX","zipcode_valid":"18100","city_valid":"VIERZON"}],"18201":[{"city":"ST AMAND MONTROND CEDEX","zipcode_valid":"18200","city_valid":"ST AMAND MONTROND"}],"18202":[{"city":"ST AMAND MONTROND CEDEX","zipcode_valid":"18200","city_valid":"ST AMAND MONTROND"}],"18203":[{"city":"ST AMAND MONTROND CEDEX","zipcode_valid":"18200","city_valid":"ST AMAND MONTROND"}],"18204":[{"city":"ST AMAND MONTROND CEDEX","zipcode_valid":"18200","city_valid":"ST AMAND MONTROND"}],"18205":[{"city":"ST AMAND MONTROND CEDEX","zipcode_valid":"18200","city_valid":"ST AMAND MONTROND"}],"18206":[{"city":"ST AMAND MONTROND CEDEX","zipcode_valid":"18200","city_valid":"ST AMAND MONTROND"}],"18207":[{"city":"ST AMAND MONTROND CEDEX","zipcode_valid":"18200","city_valid":"ST AMAND MONTROND"}],"18208":[{"city":"ST AMAND MONTROND CEDEX","zipcode_valid":"18200","city_valid":"ORVAL"}],"18209":[{"city":"ST AMAND MONTROND CEDEX","zipcode_valid":"18200","city_valid":"ST AMAND MONTROND"}],"18910":[{"city":"BOURGES CEDEX 9","zipcode_valid":"18000","city_valid":"BOURGES"}],"18911":[{"city":"BOURGES CEDEX 9","zipcode_valid":"18000","city_valid":"BOURGES"}],"18920":[{"city":"BOURGES CEDEX 9","zipcode_valid":"18000","city_valid":"BOURGES"}],"18921":[{"city":"BOURGES CEDEX 9","zipcode_valid":"18000","city_valid":"BOURGES"}],"18922":[{"city":"BOURGES CEDEX 9","zipcode_valid":"18000","city_valid":"BOURGES"}],"18923":[{"city":"BOURGES CEDEX 9","zipcode_valid":"18000","city_valid":"BOURGES"}],"18924":[{"city":"BOURGES CEDEX 9","zipcode_valid":"18000","city_valid":"BOURGES"}],"18930":[{"city":"BOURGES CEDEX 9","zipcode_valid":"18000","city_valid":"BOURGES"}],"18931":[{"city":"BOURGES CEDEX 9","zipcode_valid":"18000","city_valid":"BOURGES"}],"18932":[{"city":"BOURGES CEDEX 9","zipcode_valid":"18000","city_valid":"BOURGES"}],"18933":[{"city":"BOURGES CEDEX 9","zipcode_valid":"18000","city_valid":"BOURGES"}],"18934":[{"city":"BOURGES CEDEX 9","zipcode_valid":"18000","city_valid":"BOURGES"}],"18935":[{"city":"BOURGES CEDEX 9","zipcode_valid":"18000","city_valid":"BOURGES"}],"18939":[{"city":"BOURGES CEDEX 9","zipcode_valid":"18000","city_valid":"BOURGES"}],"18940":[{"city":"BOURGES CEDEX 9","zipcode_valid":"18000","city_valid":"BOURGES"}],"18941":[{"city":"BOURGES CEDEX 9","zipcode_valid":"18000","city_valid":"BOURGES"}],"18945":[{"city":"BOURGES CEDEX 9","zipcode_valid":"18000","city_valid":"BOURGES"}],"18998":[{"city":"AVORD CEDEX","zipcode_valid":"18520","city_valid":"AVORD"}]}