{"56001":[{"city":"VANNES CEDEX","zipcode_valid":"56000","city_valid":"VANNES"}],"56002":[{"city":"VANNES CEDEX","zipcode_valid":"56000","city_valid":"VANNES"}],"56003":[{"city":"VANNES CEDEX","zipcode_valid":"56000","city_valid":"VANNES"}],"56004":[{"city":"VANNES CEDEX","zipcode_valid":"56000","city_valid":"VANNES"}],"56005":[{"city":"VANNES CEDEX","zipcode_valid":"56000","city_valid":"VANNES"}],"56006":[{"city":"VANNES CEDEX","zipcode_valid":"56000","city_valid":"VANNES"}],"56007":[{"city":"VANNES CEDEX","zipcode_valid":"56000","city_valid":"VANNES"}],"56008":[{"city":"VANNES CEDEX","zipcode_valid":"56000","city_valid":"VANNES"}],"56009":[{"city":"VANNES CEDEX","zipcode_valid":"56000","city_valid":"VANNES"}],"56010":[{"city":"VANNES CEDEX","zipcode_valid":"56000","city_valid":"VANNES"}],"56011":[{"city":"VANNES CEDEX","zipcode_valid":"56000","city_valid":"VANNES"}],"56012":[{"city":"VANNES CEDEX","zipcode_valid":"56000","city_valid":"VANNES"}],"56013":[{"city":"VANNES CEDEX","zipcode_valid":"56000","city_valid":"VANNES"}],"56014":[{"city":"VANNES CEDEX","zipcode_valid":"56000","city_valid":"VANNES"}],"56015":[{"city":"VANNES CEDEX","zipcode_valid":"56000","city_valid":"VANNES"}],"56016":[{"city":"VANNES CEDEX","zipcode_valid":"56000","city_valid":"VANNES"}],"56017":[{"city":"VANNES CEDEX","zipcode_valid":"56000","city_valid":"VANNES"}],"56018":[{"city":"VANNES CEDEX","zipcode_valid":"56000","city_valid":"VANNES"}],"56019":[{"city":"VANNES CEDEX","zipcode_valid":"56000","city_valid":"VANNES"}],"56020":[{"city":"VANNES CEDEX","zipcode_valid":"56000","city_valid":"VANNES"}],"56021":[{"city":"VANNES CEDEX","zipcode_valid":"56000","city_valid":"VANNES"}],"56022":[{"city":"VANNES CEDEX","zipcode_valid":"56000","city_valid":"VANNES"}],"56023":[{"city":"VANNES CEDEX","zipcode_valid":"56000","city_valid":"VANNES"}],"56024":[{"city":"VANNES CEDEX","zipcode_valid":"56000","city_valid":"VANNES"}],"56025":[{"city":"VANNES CEDEX","zipcode_valid":"56000","city_valid":"VANNES"}],"56026":[{"city":"VANNES CEDEX","zipcode_valid":"56000","city_valid":"VANNES"}],"56027":[{"city":"VANNES CEDEX","zipcode_valid":"56000","city_valid":"VANNES"}],"56028":[{"city":"VANNES CEDEX","zipcode_valid":"56000","city_valid":"VANNES"}],"56029":[{"city":"VANNES CEDEX","zipcode_valid":"56000","city_valid":"VANNES"}],"56030":[{"city":"VANNES CEDEX","zipcode_valid":"56000","city_valid":"VANNES"}],"56031":[{"city":"VANNES CEDEX","zipcode_valid":"56000","city_valid":"VANNES"}],"56032":[{"city":"VANNES CEDEX","zipcode_valid":"56000","city_valid":"VANNES"}],"56033":[{"city":"VANNES CEDEX","zipcode_valid":"56000","city_valid":"VANNES"}],"56034":[{"city":"VANNES CEDEX","zipcode_valid":"56000","city_valid":"VANNES"}],"56035":[{"city":"VANNES CEDEX","zipcode_valid":"56000","city_valid":"VANNES"}],"56036":[{"city":"VANNES CEDEX","zipcode_valid":"56000","city_valid":"VANNES"}],"56037":[{"city":"VANNES CEDEX","zipcode_valid":"56000","city_valid":"VANNES"}],"56038":[{"city":"VANNES CEDEX","zipcode_valid":"56000","city_valid":"VANNES"}],"56039":[{"city":"VANNES CEDEX","zipcode_valid":"56000","city_valid":"VANNES"}],"56040":[{"city":"VANNES CEDEX","zipcode_valid":"56000","city_valid":"VANNES"}],"56101":[{"city":"LORIENT CEDEX","zipcode_valid":"56100","city_valid":"LORIENT"}],"56102":[{"city":"LORIENT CEDEX","zipcode_valid":"56100","city_valid":"LORIENT"}],"56103":[{"city":"LORIENT CEDEX","zipcode_valid":"56100","city_valid":"LORIENT"}],"56104":[{"city":"LORIENT CEDEX","zipcode_valid":"56100","city_valid":"LORIENT"}],"56105":[{"city":"LORIENT CEDEX","zipcode_valid":"56100","city_valid":"LORIENT"}],"56106":[{"city":"LORIENT CEDEX","zipcode_valid":"56100","city_valid":"LORIENT"}],"56107":[{"city":"LORIENT CEDEX","zipcode_valid":"56100","city_valid":"LORIENT"}],"56108":[{"city":"LORIENT CEDEX","zipcode_valid":"56100","city_valid":"LORIENT"}],"56109":[{"city":"LORIENT CEDEX","zipcode_valid":"56100","city_valid":"LORIENT"}],"56171":[{"city":"QUIBERON CEDEX","zipcode_valid":"56170","city_valid":"QUIBERON"}],"56172":[{"city":"QUIBERON CEDEX","zipcode_valid":"56170","city_valid":"QUIBERON"}],"56173":[{"city":"QUIBERON CEDEX","zipcode_valid":"56170","city_valid":"QUIBERON"}],"56174":[{"city":"QUIBERON CEDEX","zipcode_valid":"56170","city_valid":"QUIBERON"}],"56175":[{"city":"QUIBERON CEDEX","zipcode_valid":"56170","city_valid":"QUIBERON"}],"56176":[{"city":"QUIBERON CEDEX","zipcode_valid":"56170","city_valid":"QUIBERON"}],"56177":[{"city":"QUIBERON CEDEX","zipcode_valid":"56170","city_valid":"QUIBERON"}],"56178":[{"city":"QUIBERON CEDEX","zipcode_valid":"56170","city_valid":"QUIBERON"}],"56179":[{"city":"QUIBERON CEDEX","zipcode_valid":"56170","city_valid":"QUIBERON"}],"56201":[{"city":"LA GACILLY CEDEX","zipcode_valid":"56200","city_valid":"LA GACILLY"}],"56202":[{"city":"LA GACILLY CEDEX","zipcode_valid":"56200","city_valid":"LA GACILLY"}],"56203":[{"city":"LA GACILLY CEDEX","zipcode_valid":"56200","city_valid":"LA GACILLY"}],"56204":[{"city":"LA GACILLY CEDEX","zipcode_valid":"56200","city_valid":"LA GACILLY"}],"56205":[{"city":"LA GACILLY CEDEX","zipcode_valid":"56200","city_valid":"LA GACILLY"}],"56206":[{"city":"LA GACILLY CEDEX","zipcode_valid":"56200","city_valid":"LA GACILLY"}],"56207":[{"city":"LA GACILLY CEDEX","zipcode_valid":"56200","city_valid":"LES FOUGERETS"}],"56208":[{"city":"LA GACILLY CEDEX","zipcode_valid":"56200","city_valid":"LA GACILLY"}],"56209":[{"city":"LA GACILLY CEDEX","zipcode_valid":"56200","city_valid":"LA GACILLY"}],"56210":[{"city":"LA GACILLY CEDEX","zipcode_valid":"56200","city_valid":"LA GACILLY"}],"56211":[{"city":"LA GACILLY CEDEX","zipcode_valid":"56200","city_valid":"LA GACILLY"}],"56212":[{"city":"LA GACILLY CEDEX","zipcode_valid":"56200","city_valid":"LA GACILLY"}],"56213":[{"city":"LA GACILLY CEDEX","zipcode_valid":"56200","city_valid":"LA GACILLY"}],"56214":[{"city":"LA GACILLY CEDEX","zipcode_valid":"56200","city_valid":"LA GACILLY"}],"56215":[{"city":"LA GACILLY CEDEX","zipcode_valid":"56200","city_valid":"LA GACILLY"}],"56216":[{"city":"LA GACILLY CEDEX","zipcode_valid":"56200","city_valid":"LA GACILLY"}],"56217":[{"city":"LA GACILLY CEDEX","zipcode_valid":"56200","city_valid":"LA GACILLY"}],"56218":[{"city":"LA GACILLY CEDEX","zipcode_valid":"56200","city_valid":"LA GACILLY"}],"56219":[{"city":"LA GACILLY CEDEX","zipcode_valid":"56200","city_valid":"LA GACILLY"}],"56231":[{"city":"QUESTEMBERT CEDEX","zipcode_valid":"56230","city_valid":"QUESTEMBERT"}],"56232":[{"city":"QUESTEMBERT CEDEX","zipcode_valid":"56230","city_valid":"QUESTEMBERT"}],"56233":[{"city":"QUESTEMBERT CEDEX","zipcode_valid":"56230","city_valid":"QUESTEMBERT"}],"56234":[{"city":"QUESTEMBERT CEDEX","zipcode_valid":"56230","city_valid":"QUESTEMBERT"}],"56235":[{"city":"QUESTEMBERT CEDEX","zipcode_valid":"56230","city_valid":"QUESTEMBERT"}],"56236":[{"city":"QUESTEMBERT CEDEX","zipcode_valid":"56230","city_valid":"QUESTEMBERT"}],"56237":[{"city":"QUESTEMBERT CEDEX","zipcode_valid":"56230","city_valid":"QUESTEMBERT"}],"56238":[{"city":"QUESTEMBERT CEDEX","zipcode_valid":"56230","city_valid":"QUESTEMBERT"}],"56239":[{"city":"QUESTEMBERT CEDEX","zipcode_valid":"56230","city_valid":"QUESTEMBERT"}],"56271":[{"city":"PLOEMEUR CEDEX","zipcode_valid":"56270","city_valid":"PLOEMEUR"}],"56272":[{"city":"PLOEMEUR CEDEX","zipcode_valid":"56270","city_valid":"PLOEMEUR"}],"56273":[{"city":"PLOEMEUR CEDEX","zipcode_valid":"56270","city_valid":"PLOEMEUR"}],"56274":[{"city":"PLOEMEUR CEDEX","zipcode_valid":"56270","city_valid":"PLOEMEUR"}],"56275":[{"city":"PLOEMEUR CEDEX","zipcode_valid":"56270","city_valid":"PLOEMEUR"}],"56276":[{"city":"PLOEMEUR CEDEX","zipcode_valid":"56270","city_valid":"PLOEMEUR"}],"56277":[{"city":"PLOEMEUR CEDEX","zipcode_valid":"56260","city_valid":"LARMOR PLAGE"}],"56278":[{"city":"PLOEMEUR CEDEX","zipcode_valid":"56270","city_valid":"PLOEMEUR"}],"56279":[{"city":"PLOEMEUR CEDEX","zipcode_valid":"56270","city_valid":"PLOEMEUR"}],"56301":[{"city":"PONTIVY CEDEX","zipcode_valid":"56300","city_valid":"PONTIVY"}],"56302":[{"city":"PONTIVY CEDEX","zipcode_valid":"56300","city_valid":"PONTIVY"}],"56303":[{"city":"PONTIVY CEDEX","zipcode_valid":"56300","city_valid":"PONTIVY"}],"56304":[{"city":"PONTIVY CEDEX","zipcode_valid":"56300","city_valid":"PONTIVY"}],"56305":[{"city":"PONTIVY CEDEX","zipcode_valid":"56300","city_valid":"PONTIVY"}],"56306":[{"city":"PONTIVY CEDEX","zipcode_valid":"56300","city_valid":"PONTIVY"}],"56307":[{"city":"PONTIVY CEDEX","zipcode_valid":"56300","city_valid":"PONTIVY"}],"56308":[{"city":"PONTIVY CEDEX","zipcode_valid":"56300","city_valid":"PONTIVY"}],"56309":[{"city":"PONTIVY CEDEX","zipcode_valid":"56300","city_valid":"PONTIVY"}],"56311":[{"city":"LORIENT CEDEX","zipcode_valid":"56100","city_valid":"LORIENT"}],"56312":[{"city":"LORIENT CEDEX","zipcode_valid":"56100","city_valid":"LORIENT"}],"56313":[{"city":"LORIENT CEDEX","zipcode_valid":"56100","city_valid":"LORIENT"}],"56314":[{"city":"LORIENT CEDEX","zipcode_valid":"56100","city_valid":"LORIENT"}],"56315":[{"city":"LORIENT CEDEX","zipcode_valid":"56100","city_valid":"LORIENT"}],"56316":[{"city":"LORIENT CEDEX","zipcode_valid":"56100","city_valid":"LORIENT"}],"56317":[{"city":"LORIENT CEDEX","zipcode_valid":"56100","city_valid":"LORIENT"}],"56318":[{"city":"LORIENT CEDEX","zipcode_valid":"56100","city_valid":"LORIENT"}],"56319":[{"city":"LORIENT CEDEX","zipcode_valid":"56100","city_valid":"LORIENT"}],"56321":[{"city":"LORIENT CEDEX","zipcode_valid":"56100","city_valid":"LORIENT"}],"56322":[{"city":"LORIENT CEDEX","zipcode_valid":"56100","city_valid":"LORIENT"}],"56323":[{"city":"LORIENT CEDEX","zipcode_valid":"56100","city_valid":"LORIENT"}],"56324":[{"city":"LORIENT CEDEX","zipcode_valid":"56100","city_valid":"LORIENT"}],"56325":[{"city":"LORIENT CEDEX","zipcode_valid":"56100","city_valid":"LORIENT"}],"56326":[{"city":"LORIENT CEDEX","zipcode_valid":"56100","city_valid":"LORIENT"}],"56327":[{"city":"LORIENT CEDEX","zipcode_valid":"56100","city_valid":"LORIENT"}],"56328":[{"city":"LORIENT CEDEX","zipcode_valid":"56100","city_valid":"LORIENT"}],"56329":[{"city":"LORIENT CEDEX","zipcode_valid":"56100","city_valid":"LORIENT"}],"56341":[{"city":"CARNAC CEDEX","zipcode_valid":"56340","city_valid":"CARNAC"}],"56342":[{"city":"CARNAC CEDEX","zipcode_valid":"56340","city_valid":"CARNAC"}],"56343":[{"city":"CARNAC CEDEX","zipcode_valid":"56340","city_valid":"CARNAC"}],"56344":[{"city":"CARNAC CEDEX","zipcode_valid":"56340","city_valid":"CARNAC"}],"56345":[{"city":"CARNAC CEDEX","zipcode_valid":"56340","city_valid":"CARNAC"}],"56346":[{"city":"CARNAC CEDEX","zipcode_valid":"56340","city_valid":"CARNAC"}],"56347":[{"city":"CARNAC CEDEX","zipcode_valid":"56340","city_valid":"CARNAC"}],"56348":[{"city":"CARNAC CEDEX","zipcode_valid":"56340","city_valid":"CARNAC"}],"56349":[{"city":"CARNAC CEDEX","zipcode_valid":"56340","city_valid":"CARNAC"}],"56381":[{"city":"GUER CEDEX","zipcode_valid":"56380","city_valid":"GUER"}],"56382":[{"city":"GUER CEDEX","zipcode_valid":"56380","city_valid":"GUER"}],"56383":[{"city":"GUER CEDEX","zipcode_valid":"56380","city_valid":"GUER"}],"56384":[{"city":"GUER CEDEX","zipcode_valid":"56380","city_valid":"GUER"}],"56385":[{"city":"GUER CEDEX","zipcode_valid":"56380","city_valid":"GUER"}],"56386":[{"city":"GUER CEDEX","zipcode_valid":"56380","city_valid":"GUER"}],"56387":[{"city":"GUER CEDEX","zipcode_valid":"56380","city_valid":"GUER"}],"56388":[{"city":"GUER CEDEX","zipcode_valid":"56380","city_valid":"GUER"}],"56389":[{"city":"GUER CEDEX","zipcode_valid":"56380","city_valid":"GUER"}],"56401":[{"city":"AURAY CEDEX","zipcode_valid":"56400","city_valid":"AURAY"}],"56402":[{"city":"AURAY CEDEX","zipcode_valid":"56400","city_valid":"AURAY"}],"56403":[{"city":"AURAY CEDEX","zipcode_valid":"56400","city_valid":"AURAY"}],"56404":[{"city":"AURAY CEDEX","zipcode_valid":"56400","city_valid":"AURAY"}],"56405":[{"city":"AURAY CEDEX","zipcode_valid":"56400","city_valid":"AURAY"}],"56406":[{"city":"AURAY CEDEX","zipcode_valid":"56400","city_valid":"AURAY"}],"56407":[{"city":"AURAY CEDEX","zipcode_valid":"56400","city_valid":"AURAY"}],"56408":[{"city":"AURAY CEDEX","zipcode_valid":"56400","city_valid":"AURAY"}],"56409":[{"city":"AURAY CEDEX","zipcode_valid":"56400","city_valid":"AURAY"}],"56411":[{"city":"AURAY CEDEX","zipcode_valid":"56400","city_valid":"STE ANNE D AURAY"}],"56412":[{"city":"AURAY CEDEX","zipcode_valid":"56400","city_valid":"AURAY"}],"56413":[{"city":"AURAY CEDEX","zipcode_valid":"56400","city_valid":"AURAY"}],"56414":[{"city":"AURAY CEDEX","zipcode_valid":"56400","city_valid":"AURAY"}],"56415":[{"city":"AURAY CEDEX","zipcode_valid":"56400","city_valid":"AURAY"}],"56416":[{"city":"AURAY CEDEX","zipcode_valid":"56400","city_valid":"AURAY"}],"56417":[{"city":"AURAY CEDEX","zipcode_valid":"56400","city_valid":"AURAY"}],"56418":[{"city":"AURAY CEDEX","zipcode_valid":"56400","city_valid":"AURAY"}],"56419":[{"city":"AURAY CEDEX","zipcode_valid":"56400","city_valid":"AURAY"}],"56481":[{"city":"PONTIVY CEDEX","zipcode_valid":"56300","city_valid":"PONTIVY"}],"56482":[{"city":"PONTIVY CEDEX","zipcode_valid":"56300","city_valid":"PONTIVY"}],"56483":[{"city":"PONTIVY CEDEX","zipcode_valid":"56300","city_valid":"PONTIVY"}],"56484":[{"city":"PONTIVY CEDEX","zipcode_valid":"56300","city_valid":"PONTIVY"}],"56485":[{"city":"PONTIVY CEDEX","zipcode_valid":"56300","city_valid":"PONTIVY"}],"56486":[{"city":"PONTIVY CEDEX","zipcode_valid":"56300","city_valid":"PONTIVY"}],"56487":[{"city":"PONTIVY CEDEX","zipcode_valid":"56300","city_valid":"PONTIVY"}],"56488":[{"city":"PONTIVY CEDEX","zipcode_valid":"56300","city_valid":"PONTIVY"}],"56489":[{"city":"PONTIVY CEDEX","zipcode_valid":"56300","city_valid":"PONTIVY"}],"56501":[{"city":"LOCMINE CEDEX","zipcode_valid":"56500","city_valid":"LOCMINE"}],"56502":[{"city":"LOCMINE CEDEX","zipcode_valid":"56500","city_valid":"LOCMINE"}],"56503":[{"city":"LOCMINE CEDEX","zipcode_valid":"56500","city_valid":"LOCMINE"}],"56504":[{"city":"LOCMINE CEDEX","zipcode_valid":"56500","city_valid":"REGUINY"}],"56505":[{"city":"LOCMINE CEDEX","zipcode_valid":"56500","city_valid":"LOCMINE"}],"56506":[{"city":"LOCMINE CEDEX","zipcode_valid":"56500","city_valid":"LOCMINE"}],"56507":[{"city":"LOCMINE CEDEX","zipcode_valid":"56500","city_valid":"LOCMINE"}],"56508":[{"city":"LOCMINE CEDEX","zipcode_valid":"56500","city_valid":"LOCMINE"}],"56509":[{"city":"LOCMINE CEDEX","zipcode_valid":"56500","city_valid":"LOCMINE"}],"56531":[{"city":"QUEVEN CEDEX","zipcode_valid":"56530","city_valid":"QUEVEN"}],"56532":[{"city":"QUEVEN CEDEX","zipcode_valid":"56530","city_valid":"QUEVEN"}],"56533":[{"city":"QUEVEN CEDEX","zipcode_valid":"56530","city_valid":"QUEVEN"}],"56534":[{"city":"QUEVEN CEDEX","zipcode_valid":"56530","city_valid":"QUEVEN"}],"56535":[{"city":"QUEVEN CEDEX","zipcode_valid":"56530","city_valid":"QUEVEN"}],"56536":[{"city":"QUEVEN CEDEX","zipcode_valid":"56530","city_valid":"QUEVEN"}],"56537":[{"city":"QUEVEN CEDEX","zipcode_valid":"56530","city_valid":"QUEVEN"}],"56538":[{"city":"QUEVEN CEDEX","zipcode_valid":"56530","city_valid":"QUEVEN"}],"56539":[{"city":"QUEVEN CEDEX","zipcode_valid":"56530","city_valid":"QUEVEN"}],"56601":[{"city":"LANESTER CEDEX","zipcode_valid":"56600","city_valid":"LANESTER"}],"56602":[{"city":"LANESTER CEDEX","zipcode_valid":"56600","city_valid":"LANESTER"}],"56603":[{"city":"LANESTER CEDEX","zipcode_valid":"56850","city_valid":"CAUDAN"}],"56604":[{"city":"LANESTER CEDEX","zipcode_valid":"56600","city_valid":"LANESTER"}],"56605":[{"city":"LANESTER CEDEX","zipcode_valid":"56600","city_valid":"LANESTER"}],"56606":[{"city":"LANESTER CEDEX","zipcode_valid":"56600","city_valid":"LANESTER"}],"56607":[{"city":"LANESTER CEDEX","zipcode_valid":"56600","city_valid":"LANESTER"}],"56608":[{"city":"LANESTER CEDEX","zipcode_valid":"56600","city_valid":"LANESTER"}],"56609":[{"city":"LANESTER CEDEX","zipcode_valid":"56600","city_valid":"LANESTER"}],"56701":[{"city":"HENNEBONT CEDEX","zipcode_valid":"56700","city_valid":"HENNEBONT"}],"56702":[{"city":"HENNEBONT CEDEX","zipcode_valid":"56700","city_valid":"HENNEBONT"}],"56703":[{"city":"HENNEBONT CEDEX","zipcode_valid":"56700","city_valid":"HENNEBONT"}],"56704":[{"city":"HENNEBONT CEDEX","zipcode_valid":"56700","city_valid":"HENNEBONT"}],"56705":[{"city":"HENNEBONT CEDEX","zipcode_valid":"56440","city_valid":"LANGUIDIC"}],"56706":[{"city":"HENNEBONT CEDEX","zipcode_valid":"56700","city_valid":"HENNEBONT"}],"56707":[{"city":"HENNEBONT CEDEX","zipcode_valid":"56700","city_valid":"HENNEBONT"}],"56708":[{"city":"HENNEBONT CEDEX","zipcode_valid":"56700","city_valid":"HENNEBONT"}],"56709":[{"city":"HENNEBONT CEDEX","zipcode_valid":"56440","city_valid":"LANGUIDIC"}],"56801":[{"city":"PLOERMEL CEDEX","zipcode_valid":"56800","city_valid":"PLOERMEL"}],"56802":[{"city":"PLOERMEL CEDEX","zipcode_valid":"56800","city_valid":"PLOERMEL"}],"56803":[{"city":"PLOERMEL CEDEX","zipcode_valid":"56800","city_valid":"PLOERMEL"}],"56804":[{"city":"PLOERMEL CEDEX","zipcode_valid":"56800","city_valid":"PLOERMEL"}],"56805":[{"city":"PLOERMEL CEDEX","zipcode_valid":"56800","city_valid":"PLOERMEL"}],"56806":[{"city":"PLOERMEL CEDEX","zipcode_valid":"56800","city_valid":"PLOERMEL"}],"56807":[{"city":"PLOERMEL CEDEX","zipcode_valid":"56800","city_valid":"PLOERMEL"}],"56808":[{"city":"PLOERMEL CEDEX","zipcode_valid":"56800","city_valid":"PLOERMEL"}],"56809":[{"city":"PLOERMEL CEDEX","zipcode_valid":"56800","city_valid":"PLOERMEL"}],"56851":[{"city":"CAUDAN CEDEX","zipcode_valid":"56850","city_valid":"CAUDAN"}],"56852":[{"city":"CAUDAN CEDEX","zipcode_valid":"56850","city_valid":"CAUDAN"}],"56853":[{"city":"CAUDAN CEDEX","zipcode_valid":"56850","city_valid":"CAUDAN"}],"56854":[{"city":"CAUDAN CEDEX","zipcode_valid":"56850","city_valid":"CAUDAN"}],"56855":[{"city":"CAUDAN CEDEX","zipcode_valid":"56850","city_valid":"CAUDAN"}],"56891":[{"city":"ST AVE CEDEX","zipcode_valid":"56890","city_valid":"ST AVE"}],"56892":[{"city":"ST AVE CEDEX","zipcode_valid":"56890","city_valid":"ST AVE"}],"56893":[{"city":"ST AVE CEDEX","zipcode_valid":"56890","city_valid":"ST AVE"}],"56894":[{"city":"ST AVE CEDEX","zipcode_valid":"56890","city_valid":"ST AVE"}],"56895":[{"city":"ST AVE CEDEX","zipcode_valid":"56890","city_valid":"ST AVE"}],"56896":[{"city":"ST AVE CEDEX","zipcode_valid":"56890","city_valid":"ST AVE"}],"56897":[{"city":"ST AVE CEDEX","zipcode_valid":"56890","city_valid":"ST AVE"}],"56898":[{"city":"ST AVE CEDEX","zipcode_valid":"56890","city_valid":"ST AVE"}],"56899":[{"city":"ST AVE CEDEX","zipcode_valid":"56890","city_valid":"ST AVE"}],"56900":[{"city":"VANNES CEDEX 9","zipcode_valid":"56200","city_valid":"LA GACILLY"}],"56901":[{"city":"VANNES CEDEX 9","zipcode_valid":"56000","city_valid":"VANNES"}],"56902":[{"city":"VANNES CEDEX 9","zipcode_valid":"56200","city_valid":"LES FOUGERETS"}],"56903":[{"city":"VANNES CEDEX 9","zipcode_valid":"56000","city_valid":"VANNES"}],"56904":[{"city":"VANNES CEDEX 9","zipcode_valid":"56000","city_valid":"VANNES"}],"56905":[{"city":"VANNES CEDEX 9","zipcode_valid":"56000","city_valid":"VANNES"}],"56906":[{"city":"VANNES CEDEX 9","zipcode_valid":"56000","city_valid":"VANNES"}],"56907":[{"city":"VANNES CEDEX 9","zipcode_valid":"56000","city_valid":"VANNES"}],"56908":[{"city":"VANNES CEDEX 9","zipcode_valid":"56000","city_valid":"VANNES"}],"56909":[{"city":"VANNES CEDEX 9","zipcode_valid":"56000","city_valid":"VANNES"}],"56951":[{"city":"VANNES CEDEX 9","zipcode_valid":"56000","city_valid":"VANNES"}],"56952":[{"city":"VANNES CEDEX 9","zipcode_valid":"56000","city_valid":"VANNES"}],"56953":[{"city":"VANNES CEDEX 9","zipcode_valid":"56000","city_valid":"VANNES"}],"56954":[{"city":"VANNES CEDEX 9","zipcode_valid":"56000","city_valid":"VANNES"}],"56955":[{"city":"VANNES CEDEX 9","zipcode_valid":"56000","city_valid":"VANNES"}],"56956":[{"city":"VANNES CEDEX 9","zipcode_valid":"56000","city_valid":"VANNES"}],"56957":[{"city":"VANNES CEDEX 9","zipcode_valid":"56800","city_valid":"GUILLAC"}],"56958":[{"city":"VANNES CEDEX 9","zipcode_valid":"56000","city_valid":"VANNES"}],"56959":[{"city":"VANNES CEDEX 9","zipcode_valid":"56000","city_valid":"VANNES"}],"56960":[{"city":"VANNES CEDEX 9","zipcode_valid":"56000","city_valid":"VANNES"}],"56961":[{"city":"VANNES CEDEX 9","zipcode_valid":"56000","city_valid":"VANNES"}],"56962":[{"city":"VANNES CEDEX 9","zipcode_valid":"56000","city_valid":"VANNES"}],"56963":[{"city":"VANNES CEDEX 9","zipcode_valid":"56000","city_valid":"VANNES"}],"56964":[{"city":"VANNES CEDEX 9","zipcode_valid":"56000","city_valid":"VANNES"}],"56965":[{"city":"VANNES CEDEX 9","zipcode_valid":"56000","city_valid":"VANNES"}],"56966":[{"city":"VANNES CEDEX 9","zipcode_valid":"56000","city_valid":"VANNES"}],"56967":[{"city":"VANNES CEDEX 9","zipcode_valid":"56000","city_valid":"VANNES"}],"56968":[{"city":"VANNES CEDEX 9","zipcode_valid":"56000","city_valid":"VANNES"}],"56969":[{"city":"VANNES CEDEX 9","zipcode_valid":"56000","city_valid":"VANNES"}],"56970":[{"city":"VANNES CEDEX 9","zipcode_valid":"56000","city_valid":"VANNES"}],"56973":[{"city":"VANNES CEDEX 9","zipcode_valid":"56000","city_valid":"VANNES"}],"56977":[{"city":"VANNES CEDEX 9","zipcode_valid":"56000","city_valid":"VANNES"}],"56979":[{"city":"VANNES CEDEX 9","zipcode_valid":"56000","city_valid":"VANNES"}],"56998":[{"city":"LORIENT CEDEX","zipcode_valid":"56100","city_valid":"LORIENT"}]}