{"92001":[{"city":"NANTERRE CEDEX","zipcode_valid":"92000","city_valid":"NANTERRE"}],"92002":[{"city":"NANTERRE CEDEX","zipcode_valid":"92000","city_valid":"NANTERRE"}],"92003":[{"city":"NANTERRE CEDEX","zipcode_valid":"92000","city_valid":"NANTERRE"}],"92004":[{"city":"NANTERRE CEDEX","zipcode_valid":"92000","city_valid":"NANTERRE"}],"92005":[{"city":"NANTERRE CEDEX","zipcode_valid":"92000","city_valid":"NANTERRE"}],"92006":[{"city":"NANTERRE CEDEX","zipcode_valid":"92000","city_valid":"NANTERRE"}],"92007":[{"city":"NANTERRE CEDEX","zipcode_valid":"92000","city_valid":"NANTERRE"}],"92008":[{"city":"NANTERRE CEDEX","zipcode_valid":"92000","city_valid":"NANTERRE"}],"92009":[{"city":"NANTERRE CEDEX","zipcode_valid":"92000","city_valid":"NANTERRE"}],"92010":[{"city":"NANTERRE CEDEX","zipcode_valid":"92000","city_valid":"NANTERRE"}],"92011":[{"city":"NANTERRE CEDEX","zipcode_valid":"92000","city_valid":"NANTERRE"}],"92012":[{"city":"NANTERRE CEDEX","zipcode_valid":"92000","city_valid":"NANTERRE"}],"92013":[{"city":"NANTERRE CEDEX","zipcode_valid":"92000","city_valid":"NANTERRE"}],"92014":[{"city":"NANTERRE CEDEX","zipcode_valid":"92000","city_valid":"NANTERRE"}],"92015":[{"city":"NANTERRE CEDEX","zipcode_valid":"92000","city_valid":"NANTERRE"}],"92016":[{"city":"NANTERRE CEDEX","zipcode_valid":"92000","city_valid":"NANTERRE"}],"92017":[{"city":"NANTERRE CEDEX","zipcode_valid":"92000","city_valid":"NANTERRE"}],"92018":[{"city":"NANTERRE CEDEX","zipcode_valid":"92000","city_valid":"NANTERRE"}],"92019":[{"city":"NANTERRE CEDEX","zipcode_valid":"92000","city_valid":"NANTERRE"}],"92020":[{"city":"NANTERRE CEDEX","zipcode_valid":"92000","city_valid":"NANTERRE"}],"92021":[{"city":"NANTERRE CEDEX","zipcode_valid":"92000","city_valid":"NANTERRE"}],"92022":[{"city":"NANTERRE CEDEX","zipcode_valid":"92000","city_valid":"NANTERRE"}],"92023":[{"city":"NANTERRE CEDEX","zipcode_valid":"92000","city_valid":"NANTERRE"}],"92024":[{"city":"NANTERRE CEDEX","zipcode_valid":"92000","city_valid":"NANTERRE"}],"92025":[{"city":"NANTERRE CEDEX","zipcode_valid":"92000","city_valid":"NANTERRE"}],"92026":[{"city":"NANTERRE CEDEX","zipcode_valid":"92000","city_valid":"NANTERRE"}],"92027":[{"city":"NANTERRE CEDEX","zipcode_valid":"92000","city_valid":"NANTERRE"}],"92028":[{"city":"NANTERRE CEDEX","zipcode_valid":"92000","city_valid":"NANTERRE"}],"92029":[{"city":"NANTERRE CEDEX","zipcode_valid":"92000","city_valid":"NANTERRE"}],"92030":[{"city":"PARIS LA DEFENSE CEDEX","zipcode_valid":"92999","city_valid":"PARIS LA DEFENSE"}],"92031":[{"city":"PARIS LA DEFENSE CEDEX","zipcode_valid":"92800","city_valid":"PUTEAUX"}],"92032":[{"city":"PARIS LA DEFENSE CEDEX","zipcode_valid":"92999","city_valid":"PARIS LA DEFENSE"}],"92033":[{"city":"PARIS LA DEFENSE CEDEX","zipcode_valid":"92400","city_valid":"COURBEVOIE"}],"92034":[{"city":"PARIS LA DEFENSE CEDEX","zipcode_valid":"92800","city_valid":"PUTEAUX"}],"92035":[{"city":"PARIS LA DEFENSE CEDEX","zipcode_valid":"92800","city_valid":"PUTEAUX"}],"92036":[{"city":"PARIS LA DEFENSE CEDEX","zipcode_valid":"92400","city_valid":"COURBEVOIE"}],"92037":[{"city":"PARIS LA DEFENSE CEDEX","zipcode_valid":"92400","city_valid":"COURBEVOIE"}],"92038":[{"city":"PARIS LA DEFENSE CEDEX","zipcode_valid":"92999","city_valid":"PARIS LA DEFENSE"}],"92039":[{"city":"PARIS LA DEFENSE CEDEX","zipcode_valid":"92800","city_valid":"PUTEAUX"}],"92040":[{"city":"PARIS LA DEFENSE CEDEX","zipcode_valid":"92999","city_valid":"PARIS LA DEFENSE"}],"92041":[{"city":"PARIS LA DEFENSE CEDEX","zipcode_valid":"92400","city_valid":"COURBEVOIE"}],"92042":[{"city":"PARIS LA DEFENSE CEDEX","zipcode_valid":"92800","city_valid":"PUTEAUX"}],"92043":[{"city":"PARIS LA DEFENSE CEDEX","zipcode_valid":"92400","city_valid":"COURBEVOIE"}],"92044":[{"city":"PARIS LA DEFENSE CEDEX","zipcode_valid":"92800","city_valid":"PUTEAUX"}],"92045":[{"city":"PARIS LA DEFENSE CEDEX","zipcode_valid":"92800","city_valid":"PUTEAUX"}],"92046":[{"city":"PARIS LA DEFENSE CEDEX","zipcode_valid":"92800","city_valid":"PUTEAUX"}],"92047":[{"city":"PARIS LA DEFENSE CEDEX","zipcode_valid":"92800","city_valid":"PUTEAUX"}],"92048":[{"city":"PARIS LA DEFENSE CEDEX","zipcode_valid":"92400","city_valid":"COURBEVOIE"}],"92049":[{"city":"PARIS LA DEFENSE CEDEX","zipcode_valid":"92400","city_valid":"COURBEVOIE"}],"92050":[{"city":"PARIS LA DEFENSE CEDEX","zipcode_valid":"92400","city_valid":"COURBEVOIE"}],"92051":[{"city":"PARIS LA DEFENSE CEDEX","zipcode_valid":"92400","city_valid":"COURBEVOIE"}],"92052":[{"city":"PARIS LA DEFENSE CEDEX","zipcode_valid":"92400","city_valid":"COURBEVOIE"}],"92053":[{"city":"PARIS LA DEFENSE CEDEX","zipcode_valid":"92800","city_valid":"PUTEAUX"}],"92054":[{"city":"PARIS LA DEFENSE CEDEX","zipcode_valid":"92400","city_valid":"COURBEVOIE"}],"92055":[{"city":"PARIS LA DEFENSE CEDEX","zipcode_valid":"92800","city_valid":"PUTEAUX"}],"92056":[{"city":"PARIS LA DEFENSE CEDEX","zipcode_valid":"92800","city_valid":"PUTEAUX"}],"92057":[{"city":"PARIS LA DEFENSE CEDEX","zipcode_valid":"92800","city_valid":"PUTEAUX"}],"92058":[{"city":"PARIS LA DEFENSE CEDEX","zipcode_valid":"92800","city_valid":"PUTEAUX"}],"92059":[{"city":"PARIS LA DEFENSE CEDEX","zipcode_valid":"92999","city_valid":"PARIS LA DEFENSE"}],"92060":[{"city":"PARIS LA DEFENSE CEDEX","zipcode_valid":"92800","city_valid":"PUTEAUX"}],"92061":[{"city":"PARIS LA DEFENSE CEDEX","zipcode_valid":"92400","city_valid":"COURBEVOIE"}],"92062":[{"city":"PARIS LA DEFENSE CEDEX","zipcode_valid":"92400","city_valid":"COURBEVOIE"}],"92063":[{"city":"PARIS LA DEFENSE CEDEX","zipcode_valid":"92400","city_valid":"COURBEVOIE"}],"92064":[{"city":"PARIS LA DEFENSE CEDEX","zipcode_valid":"92800","city_valid":"PUTEAUX"}],"92065":[{"city":"PARIS LA DEFENSE CEDEX","zipcode_valid":"92800","city_valid":"PUTEAUX"}],"92066":[{"city":"PARIS LA DEFENSE CEDEX","zipcode_valid":"92400","city_valid":"COURBEVOIE"}],"92067":[{"city":"PARIS LA DEFENSE CEDEX","zipcode_valid":"92800","city_valid":"PUTEAUX"}],"92068":[{"city":"PARIS LA DEFENSE CEDEX","zipcode_valid":"92400","city_valid":"COURBEVOIE"}],"92069":[{"city":"PARIS LA DEFENSE CEDEX","zipcode_valid":"92400","city_valid":"COURBEVOIE"}],"92070":[{"city":"PARIS LA DEFENSE CEDEX","zipcode_valid":"92400","city_valid":"COURBEVOIE"}],"92071":[{"city":"PARIS LA DEFENSE CEDEX","zipcode_valid":"92800","city_valid":"PUTEAUX"}],"92072":[{"city":"PARIS LA DEFENSE CEDEX","zipcode_valid":"92400","city_valid":"COURBEVOIE"}],"92073":[{"city":"PARIS LA DEFENSE CEDEX","zipcode_valid":"92800","city_valid":"PUTEAUX"}],"92074":[{"city":"PARIS LA DEFENSE CEDEX","zipcode_valid":"92800","city_valid":"PUTEAUX"}],"92075":[{"city":"PARIS LA DEFENSE CEDEX","zipcode_valid":"92400","city_valid":"COURBEVOIE"}],"92076":[{"city":"PARIS LA DEFENSE CEDEX","zipcode_valid":"92800","city_valid":"PUTEAUX"}],"92077":[{"city":"PARIS LA DEFENSE CEDEX","zipcode_valid":"92999","city_valid":"PARIS LA DEFENSE"}],"92078":[{"city":"PARIS LA DEFENSE CEDEX","zipcode_valid":"92400","city_valid":"COURBEVOIE"}],"92079":[{"city":"PARIS LA DEFENSE CEDEX","zipcode_valid":"92400","city_valid":"COURBEVOIE"}],"92080":[{"city":"PARIS LA DEFENSE CEDEX","zipcode_valid":"92999","city_valid":"PARIS LA DEFENSE"}],"92081":[{"city":"PARIS LA DEFENSE CEDEX","zipcode_valid":"92800","city_valid":"PUTEAUX"}],"92082":[{"city":"PARIS LA DEFENSE CEDEX","zipcode_valid":"92800","city_valid":"PUTEAUX"}],"92083":[{"city":"PARIS LA DEFENSE CEDEX","zipcode_valid":"92400","city_valid":"COURBEVOIE"}],"92084":[{"city":"PARIS LA DEFENSE CEDEX","zipcode_valid":"92400","city_valid":"COURBEVOIE"}],"92085":[{"city":"PARIS LA DEFENSE CEDEX","zipcode_valid":"92800","city_valid":"PUTEAUX"}],"92086":[{"city":"PARIS LA DEFENSE CEDEX","zipcode_valid":"92400","city_valid":"COURBEVOIE"}],"92087":[{"city":"PARIS LA DEFENSE CEDEX","zipcode_valid":"92999","city_valid":"PARIS LA DEFENSE"}],"92088":[{"city":"PARIS LA DEFENSE CEDEX","zipcode_valid":"92800","city_valid":"PUTEAUX"}],"92089":[{"city":"PARIS LA DEFENSE CEDEX","zipcode_valid":"92800","city_valid":"PUTEAUX"}],"92090":[{"city":"PARIS LA DEFENSE CEDEX","zipcode_valid":"92999","city_valid":"PARIS LA DEFENSE"}],"92091":[{"city":"PARIS LA DEFENSE CEDEX","zipcode_valid":"92400","city_valid":"COURBEVOIE"}],"92092":[{"city":"PARIS LA DEFENSE CEDEX","zipcode_valid":"92800","city_valid":"PUTEAUX"}],"92093":[{"city":"PARIS LA DEFENSE CEDEX","zipcode_valid":"92800","city_valid":"PUTEAUX"}],"92094":[{"city":"PARIS LA DEFENSE CEDEX","zipcode_valid":"92999","city_valid":"PARIS LA DEFENSE"}],"92095":[{"city":"PARIS LA DEFENSE CEDEX","zipcode_valid":"92999","city_valid":"PARIS LA DEFENSE"}],"92096":[{"city":"PARIS LA DEFENSE CEDEX","zipcode_valid":"92400","city_valid":"COURBEVOIE"}],"92097":[{"city":"PARIS LA DEFENSE CEDEX","zipcode_valid":"92999","city_valid":"PARIS LA DEFENSE"}],"92098":[{"city":"PARIS LA DEFENSE CEDEX","zipcode_valid":"92999","city_valid":"PARIS LA DEFENSE"}],"92099":[{"city":"PARIS LA DEFENSE CEDEX","zipcode_valid":"92800","city_valid":"PUTEAUX"}],"92101":[{"city":"BOULOGNE BILLANCOURT CEDEX","zipcode_valid":"92100","city_valid":"BOULOGNE BILLANCOURT"}],"92102":[{"city":"BOULOGNE BILLANCOURT CEDEX","zipcode_valid":"92100","city_valid":"BOULOGNE BILLANCOURT"}],"92103":[{"city":"BOULOGNE BILLANCOURT CEDEX","zipcode_valid":"92100","city_valid":"BOULOGNE BILLANCOURT"}],"92104":[{"city":"BOULOGNE BILLANCOURT CEDEX","zipcode_valid":"92100","city_valid":"BOULOGNE BILLANCOURT"}],"92105":[{"city":"BOULOGNE BILLANCOURT CEDEX","zipcode_valid":"92100","city_valid":"BOULOGNE BILLANCOURT"}],"92106":[{"city":"BOULOGNE BILLANCOURT CEDEX","zipcode_valid":"92100","city_valid":"BOULOGNE BILLANCOURT"}],"92107":[{"city":"BOULOGNE BILLANCOURT CEDEX","zipcode_valid":"92100","city_valid":"BOULOGNE BILLANCOURT"}],"92108":[{"city":"BOULOGNE BILLANCOURT CEDEX","zipcode_valid":"92100","city_valid":"BOULOGNE BILLANCOURT"}],"92109":[{"city":"BOULOGNE BILLANCOURT CEDEX","zipcode_valid":"92100","city_valid":"BOULOGNE BILLANCOURT"}],"92111":[{"city":"CLICHY CEDEX","zipcode_valid":"92110","city_valid":"CLICHY"}],"92112":[{"city":"CLICHY CEDEX","zipcode_valid":"92110","city_valid":"CLICHY"}],"92113":[{"city":"CLICHY CEDEX","zipcode_valid":"92110","city_valid":"CLICHY"}],"92114":[{"city":"CLICHY CEDEX","zipcode_valid":"92110","city_valid":"CLICHY"}],"92115":[{"city":"CLICHY CEDEX","zipcode_valid":"92110","city_valid":"CLICHY"}],"92116":[{"city":"CLICHY CEDEX","zipcode_valid":"92110","city_valid":"CLICHY"}],"92117":[{"city":"CLICHY CEDEX","zipcode_valid":"92110","city_valid":"CLICHY"}],"92118":[{"city":"CLICHY CEDEX","zipcode_valid":"92110","city_valid":"CLICHY"}],"92119":[{"city":"CLICHY CEDEX","zipcode_valid":"92110","city_valid":"CLICHY"}],"92121":[{"city":"MONTROUGE CEDEX","zipcode_valid":"92120","city_valid":"MONTROUGE"}],"92122":[{"city":"MONTROUGE CEDEX","zipcode_valid":"92120","city_valid":"MONTROUGE"}],"92123":[{"city":"MONTROUGE CEDEX","zipcode_valid":"92120","city_valid":"MONTROUGE"}],"92124":[{"city":"MONTROUGE CEDEX","zipcode_valid":"92120","city_valid":"MONTROUGE"}],"92125":[{"city":"MONTROUGE CEDEX","zipcode_valid":"92120","city_valid":"MONTROUGE"}],"92126":[{"city":"MONTROUGE CEDEX","zipcode_valid":"92120","city_valid":"MONTROUGE"}],"92127":[{"city":"MONTROUGE CEDEX","zipcode_valid":"92120","city_valid":"MONTROUGE"}],"92128":[{"city":"MONTROUGE CEDEX","zipcode_valid":"92120","city_valid":"MONTROUGE"}],"92129":[{"city":"MONTROUGE CEDEX","zipcode_valid":"92120","city_valid":"MONTROUGE"}],"92131":[{"city":"ISSY LES MOULINEAUX CEDEX","zipcode_valid":"92130","city_valid":"ISSY LES MOULINEAUX"}],"92132":[{"city":"ISSY LES MOULINEAUX CEDEX","zipcode_valid":"92130","city_valid":"ISSY LES MOULINEAUX"}],"92133":[{"city":"ISSY LES MOULINEAUX CEDEX","zipcode_valid":"92130","city_valid":"ISSY LES MOULINEAUX"}],"92134":[{"city":"ISSY LES MOULINEAUX CEDEX","zipcode_valid":"92130","city_valid":"ISSY LES MOULINEAUX"}],"92135":[{"city":"ISSY LES MOULINEAUX CEDEX","zipcode_valid":"92130","city_valid":"ISSY LES MOULINEAUX"}],"92136":[{"city":"ISSY LES MOULINEAUX CEDEX","zipcode_valid":"92130","city_valid":"ISSY LES MOULINEAUX"}],"92137":[{"city":"ISSY LES MOULINEAUX CEDEX","zipcode_valid":"92130","city_valid":"ISSY LES MOULINEAUX"}],"92138":[{"city":"ISSY LES MOULINEAUX CEDEX","zipcode_valid":"92130","city_valid":"ISSY LES MOULINEAUX"}],"92139":[{"city":"ISSY LES MOULINEAUX CEDEX","zipcode_valid":"92130","city_valid":"ISSY LES MOULINEAUX"}],"92141":[{"city":"CLAMART CEDEX","zipcode_valid":"92140","city_valid":"CLAMART"}],"92142":[{"city":"CLAMART CEDEX","zipcode_valid":"92140","city_valid":"CLAMART"}],"92143":[{"city":"CLAMART CEDEX","zipcode_valid":"92140","city_valid":"CLAMART"}],"92144":[{"city":"CLAMART CEDEX","zipcode_valid":"92140","city_valid":"CLAMART"}],"92145":[{"city":"CLAMART CEDEX","zipcode_valid":"92140","city_valid":"CLAMART"}],"92146":[{"city":"CLAMART CEDEX","zipcode_valid":"92140","city_valid":"CLAMART"}],"92147":[{"city":"CLAMART CEDEX","zipcode_valid":"92140","city_valid":"CLAMART"}],"92148":[{"city":"CLAMART CEDEX","zipcode_valid":"92140","city_valid":"CLAMART"}],"92149":[{"city":"CLAMART CEDEX","zipcode_valid":"92140","city_valid":"CLAMART"}],"92151":[{"city":"SURESNES CEDEX","zipcode_valid":"92150","city_valid":"SURESNES"}],"92152":[{"city":"SURESNES CEDEX","zipcode_valid":"92150","city_valid":"SURESNES"}],"92153":[{"city":"SURESNES CEDEX","zipcode_valid":"92150","city_valid":"SURESNES"}],"92154":[{"city":"SURESNES CEDEX","zipcode_valid":"92150","city_valid":"SURESNES"}],"92155":[{"city":"SURESNES CEDEX","zipcode_valid":"92150","city_valid":"SURESNES"}],"92156":[{"city":"SURESNES CEDEX","zipcode_valid":"92150","city_valid":"SURESNES"}],"92157":[{"city":"SURESNES CEDEX","zipcode_valid":"92150","city_valid":"SURESNES"}],"92158":[{"city":"SURESNES CEDEX","zipcode_valid":"92150","city_valid":"SURESNES"}],"92159":[{"city":"SURESNES CEDEX","zipcode_valid":"92150","city_valid":"SURESNES"}],"92161":[{"city":"ANTONY CEDEX","zipcode_valid":"92160","city_valid":"ANTONY"}],"92162":[{"city":"ANTONY CEDEX","zipcode_valid":"92160","city_valid":"ANTONY"}],"92163":[{"city":"ANTONY CEDEX","zipcode_valid":"92160","city_valid":"ANTONY"}],"92164":[{"city":"ANTONY CEDEX","zipcode_valid":"92160","city_valid":"ANTONY"}],"92165":[{"city":"ANTONY CEDEX","zipcode_valid":"92160","city_valid":"ANTONY"}],"92166":[{"city":"ANTONY CEDEX","zipcode_valid":"92160","city_valid":"ANTONY"}],"92167":[{"city":"ANTONY CEDEX","zipcode_valid":"92160","city_valid":"ANTONY"}],"92168":[{"city":"ANTONY CEDEX","zipcode_valid":"92160","city_valid":"ANTONY"}],"92169":[{"city":"ANTONY CEDEX","zipcode_valid":"92160","city_valid":"ANTONY"}],"92171":[{"city":"VANVES CEDEX","zipcode_valid":"92170","city_valid":"VANVES"}],"92172":[{"city":"VANVES CEDEX","zipcode_valid":"92170","city_valid":"VANVES"}],"92173":[{"city":"VANVES CEDEX","zipcode_valid":"92170","city_valid":"VANVES"}],"92174":[{"city":"VANVES CEDEX","zipcode_valid":"92170","city_valid":"VANVES"}],"92175":[{"city":"VANVES CEDEX","zipcode_valid":"92170","city_valid":"VANVES"}],"92176":[{"city":"VANVES CEDEX","zipcode_valid":"92170","city_valid":"VANVES"}],"92177":[{"city":"VANVES CEDEX","zipcode_valid":"92170","city_valid":"VANVES"}],"92178":[{"city":"VANVES CEDEX","zipcode_valid":"92170","city_valid":"VANVES"}],"92179":[{"city":"VANVES CEDEX","zipcode_valid":"92170","city_valid":"VANVES"}],"92181":[{"city":"ANTONY CEDEX","zipcode_valid":"92160","city_valid":"ANTONY"}],"92182":[{"city":"ANTONY CEDEX","zipcode_valid":"92160","city_valid":"ANTONY"}],"92183":[{"city":"ANTONY CEDEX","zipcode_valid":"92160","city_valid":"ANTONY"}],"92184":[{"city":"ANTONY CEDEX","zipcode_valid":"92160","city_valid":"ANTONY"}],"92185":[{"city":"ANTONY CEDEX","zipcode_valid":"92160","city_valid":"ANTONY"}],"92186":[{"city":"ANTONY CEDEX","zipcode_valid":"92160","city_valid":"ANTONY"}],"92187":[{"city":"ANTONY CEDEX","zipcode_valid":"92160","city_valid":"ANTONY"}],"92188":[{"city":"ANTONY CEDEX","zipcode_valid":"92160","city_valid":"ANTONY"}],"92189":[{"city":"ANTONY CEDEX","zipcode_valid":"92160","city_valid":"ANTONY"}],"92191":[{"city":"MEUDON CEDEX","zipcode_valid":"92190","city_valid":"MEUDON"}],"92192":[{"city":"MEUDON CEDEX","zipcode_valid":"92190","city_valid":"MEUDON"}],"92193":[{"city":"MEUDON CEDEX","zipcode_valid":"92190","city_valid":"MEUDON"}],"92194":[{"city":"MEUDON CEDEX","zipcode_valid":"92190","city_valid":"MEUDON"}],"92195":[{"city":"MEUDON CEDEX","zipcode_valid":"92190","city_valid":"MEUDON"}],"92196":[{"city":"MEUDON CEDEX","zipcode_valid":"92190","city_valid":"MEUDON"}],"92197":[{"city":"MEUDON CEDEX","zipcode_valid":"92190","city_valid":"MEUDON"}],"92198":[{"city":"MEUDON CEDEX","zipcode_valid":"92190","city_valid":"MEUDON"}],"92199":[{"city":"MEUDON CEDEX","zipcode_valid":"92190","city_valid":"MEUDON"}],"92201":[{"city":"NEUILLY SUR SEINE CEDEX","zipcode_valid":"92200","city_valid":"NEUILLY SUR SEINE"}],"92202":[{"city":"NEUILLY SUR SEINE CEDEX","zipcode_valid":"92200","city_valid":"NEUILLY SUR SEINE"}],"92203":[{"city":"NEUILLY SUR SEINE CEDEX","zipcode_valid":"92200","city_valid":"NEUILLY SUR SEINE"}],"92204":[{"city":"NEUILLY SUR SEINE CEDEX","zipcode_valid":"92200","city_valid":"NEUILLY SUR SEINE"}],"92205":[{"city":"NEUILLY SUR SEINE CEDEX","zipcode_valid":"92200","city_valid":"NEUILLY SUR SEINE"}],"92206":[{"city":"NEUILLY SUR SEINE CEDEX","zipcode_valid":"92200","city_valid":"NEUILLY SUR SEINE"}],"92207":[{"city":"NEUILLY SUR SEINE CEDEX","zipcode_valid":"92200","city_valid":"NEUILLY SUR SEINE"}],"92208":[{"city":"NEUILLY SUR SEINE CEDEX","zipcode_valid":"92200","city_valid":"NEUILLY SUR SEINE"}],"92209":[{"city":"NEUILLY SUR SEINE CEDEX","zipcode_valid":"92200","city_valid":"NEUILLY SUR SEINE"}],"92211":[{"city":"ST CLOUD CEDEX","zipcode_valid":"92210","city_valid":"ST CLOUD"}],"92212":[{"city":"ST CLOUD CEDEX","zipcode_valid":"92210","city_valid":"ST CLOUD"}],"92213":[{"city":"ST CLOUD CEDEX","zipcode_valid":"92210","city_valid":"ST CLOUD"}],"92214":[{"city":"ST CLOUD CEDEX","zipcode_valid":"92210","city_valid":"ST CLOUD"}],"92215":[{"city":"ST CLOUD CEDEX","zipcode_valid":"92210","city_valid":"ST CLOUD"}],"92216":[{"city":"ST CLOUD CEDEX","zipcode_valid":"92210","city_valid":"ST CLOUD"}],"92217":[{"city":"ST CLOUD CEDEX","zipcode_valid":"92210","city_valid":"ST CLOUD"}],"92218":[{"city":"ST CLOUD CEDEX","zipcode_valid":"92210","city_valid":"ST CLOUD"}],"92219":[{"city":"ST CLOUD CEDEX","zipcode_valid":"92210","city_valid":"ST CLOUD"}],"92221":[{"city":"BAGNEUX CEDEX","zipcode_valid":"92220","city_valid":"BAGNEUX"}],"92222":[{"city":"BAGNEUX CEDEX","zipcode_valid":"92220","city_valid":"BAGNEUX"}],"92223":[{"city":"BAGNEUX CEDEX","zipcode_valid":"92220","city_valid":"BAGNEUX"}],"92224":[{"city":"BAGNEUX CEDEX","zipcode_valid":"92220","city_valid":"BAGNEUX"}],"92225":[{"city":"BAGNEUX CEDEX","zipcode_valid":"92220","city_valid":"BAGNEUX"}],"92226":[{"city":"BAGNEUX CEDEX","zipcode_valid":"92220","city_valid":"BAGNEUX"}],"92227":[{"city":"BAGNEUX CEDEX","zipcode_valid":"92220","city_valid":"BAGNEUX"}],"92228":[{"city":"BAGNEUX CEDEX","zipcode_valid":"92220","city_valid":"BAGNEUX"}],"92229":[{"city":"BAGNEUX CEDEX","zipcode_valid":"92220","city_valid":"BAGNEUX"}],"92231":[{"city":"GENNEVILLIERS CEDEX","zipcode_valid":"92230","city_valid":"GENNEVILLIERS"}],"92232":[{"city":"GENNEVILLIERS CEDEX","zipcode_valid":"92230","city_valid":"GENNEVILLIERS"}],"92233":[{"city":"GENNEVILLIERS CEDEX","zipcode_valid":"92230","city_valid":"GENNEVILLIERS"}],"92234":[{"city":"GENNEVILLIERS CEDEX","zipcode_valid":"92230","city_valid":"GENNEVILLIERS"}],"92235":[{"city":"GENNEVILLIERS CEDEX","zipcode_valid":"92230","city_valid":"GENNEVILLIERS"}],"92236":[{"city":"GENNEVILLIERS CEDEX","zipcode_valid":"92230","city_valid":"GENNEVILLIERS"}],"92237":[{"city":"GENNEVILLIERS CEDEX","zipcode_valid":"92230","city_valid":"GENNEVILLIERS"}],"92238":[{"city":"GENNEVILLIERS CEDEX","zipcode_valid":"92230","city_valid":"GENNEVILLIERS"}],"92239":[{"city":"GENNEVILLIERS CEDEX","zipcode_valid":"92230","city_valid":"GENNEVILLIERS"}],"92241":[{"city":"MALAKOFF CEDEX","zipcode_valid":"92240","city_valid":"MALAKOFF"}],"92242":[{"city":"MALAKOFF CEDEX","zipcode_valid":"92240","city_valid":"MALAKOFF"}],"92243":[{"city":"MALAKOFF CEDEX","zipcode_valid":"92240","city_valid":"MALAKOFF"}],"92244":[{"city":"MALAKOFF CEDEX","zipcode_valid":"92240","city_valid":"MALAKOFF"}],"92245":[{"city":"MALAKOFF CEDEX","zipcode_valid":"92240","city_valid":"MALAKOFF"}],"92246":[{"city":"MALAKOFF CEDEX","zipcode_valid":"92240","city_valid":"MALAKOFF"}],"92247":[{"city":"MALAKOFF CEDEX","zipcode_valid":"92240","city_valid":"MALAKOFF"}],"92248":[{"city":"MALAKOFF CEDEX","zipcode_valid":"92240","city_valid":"MALAKOFF"}],"92249":[{"city":"MALAKOFF CEDEX","zipcode_valid":"92240","city_valid":"MALAKOFF"}],"92251":[{"city":"LA GARENNE COLOMBES CEDEX","zipcode_valid":"92250","city_valid":"LA GARENNE COLOMBES"}],"92252":[{"city":"LA GARENNE COLOMBES CEDEX","zipcode_valid":"92250","city_valid":"LA GARENNE COLOMBES"}],"92253":[{"city":"LA GARENNE COLOMBES CEDEX","zipcode_valid":"92250","city_valid":"LA GARENNE COLOMBES"}],"92254":[{"city":"LA GARENNE COLOMBES CEDEX","zipcode_valid":"92250","city_valid":"LA GARENNE COLOMBES"}],"92255":[{"city":"LA GARENNE COLOMBES CEDEX","zipcode_valid":"92250","city_valid":"LA GARENNE COLOMBES"}],"92256":[{"city":"LA GARENNE COLOMBES CEDEX","zipcode_valid":"92250","city_valid":"LA GARENNE COLOMBES"}],"92257":[{"city":"LA GARENNE COLOMBES CEDEX","zipcode_valid":"92250","city_valid":"LA GARENNE COLOMBES"}],"92258":[{"city":"LA GARENNE COLOMBES CEDEX","zipcode_valid":"92250","city_valid":"LA GARENNE COLOMBES"}],"92259":[{"city":"LA GARENNE COLOMBES CEDEX","zipcode_valid":"92250","city_valid":"LA GARENNE COLOMBES"}],"92261":[{"city":"FONTENAY AUX ROSES CEDEX","zipcode_valid":"92260","city_valid":"FONTENAY AUX ROSES"}],"92262":[{"city":"FONTENAY AUX ROSES CEDEX","zipcode_valid":"92260","city_valid":"FONTENAY AUX ROSES"}],"92263":[{"city":"FONTENAY AUX ROSES CEDEX","zipcode_valid":"92260","city_valid":"FONTENAY AUX ROSES"}],"92264":[{"city":"SURESNES CEDEX","zipcode_valid":"92150","city_valid":"SURESNES"}],"92265":[{"city":"FONTENAY AUX ROSES CEDEX","zipcode_valid":"92260","city_valid":"FONTENAY AUX ROSES"}],"92266":[{"city":"FONTENAY AUX ROSES CEDEX","zipcode_valid":"92260","city_valid":"FONTENAY AUX ROSES"}],"92267":[{"city":"FONTENAY AUX ROSES CEDEX","zipcode_valid":"92260","city_valid":"FONTENAY AUX ROSES"}],"92268":[{"city":"SURESNES CEDEX","zipcode_valid":"92150","city_valid":"SURESNES"}],"92269":[{"city":"FONTENAY AUX ROSES CEDEX","zipcode_valid":"92260","city_valid":"FONTENAY AUX ROSES"}],"92271":[{"city":"BOIS COLOMBES CEDEX","zipcode_valid":"92270","city_valid":"BOIS COLOMBES"}],"92272":[{"city":"BOIS COLOMBES CEDEX","zipcode_valid":"92270","city_valid":"BOIS COLOMBES"}],"92273":[{"city":"BOIS COLOMBES CEDEX","zipcode_valid":"92270","city_valid":"BOIS COLOMBES"}],"92274":[{"city":"BOIS COLOMBES CEDEX","zipcode_valid":"92270","city_valid":"BOIS COLOMBES"}],"92275":[{"city":"BOIS COLOMBES CEDEX","zipcode_valid":"92270","city_valid":"BOIS COLOMBES"}],"92276":[{"city":"BOIS COLOMBES CEDEX","zipcode_valid":"92270","city_valid":"BOIS COLOMBES"}],"92277":[{"city":"BOIS COLOMBES CEDEX","zipcode_valid":"92270","city_valid":"BOIS COLOMBES"}],"92279":[{"city":"BOIS COLOMBES CEDEX","zipcode_valid":"92270","city_valid":"BOIS COLOMBES"}],"92280":[{"city":"SURESNES CEDEX","zipcode_valid":"92150","city_valid":"SURESNES"}],"92281":[{"city":"SURESNES CEDEX","zipcode_valid":"92150","city_valid":"SURESNES"}],"92282":[{"city":"SURESNES CEDEX","zipcode_valid":"92150","city_valid":"SURESNES"}],"92283":[{"city":"BAGNEUX CEDEX","zipcode_valid":"92220","city_valid":"BAGNEUX"}],"92284":[{"city":"SURESNES CEDEX","zipcode_valid":"92150","city_valid":"SURESNES"}],"92285":[{"city":"BAGNEUX CEDEX","zipcode_valid":"92220","city_valid":"BAGNEUX"}],"92286":[{"city":"SURESNES CEDEX","zipcode_valid":"92150","city_valid":"SURESNES"}],"92287":[{"city":"SURESNES CEDEX","zipcode_valid":"92150","city_valid":"SURESNES"}],"92288":[{"city":"SURESNES CEDEX","zipcode_valid":"92150","city_valid":"SURESNES"}],"92289":[{"city":"SURESNES CEDEX","zipcode_valid":"92150","city_valid":"SURESNES"}],"92291":[{"city":"CHATENAY MALABRY CEDEX","zipcode_valid":"92290","city_valid":"CHATENAY MALABRY"}],"92292":[{"city":"CHATENAY MALABRY CEDEX","zipcode_valid":"92290","city_valid":"CHATENAY MALABRY"}],"92293":[{"city":"CHATENAY MALABRY CEDEX","zipcode_valid":"92290","city_valid":"CHATENAY MALABRY"}],"92294":[{"city":"CHATENAY MALABRY CEDEX","zipcode_valid":"92290","city_valid":"CHATENAY MALABRY"}],"92295":[{"city":"CHATENAY MALABRY CEDEX","zipcode_valid":"92290","city_valid":"CHATENAY MALABRY"}],"92296":[{"city":"CHATENAY MALABRY CEDEX","zipcode_valid":"92290","city_valid":"CHATENAY MALABRY"}],"92297":[{"city":"CHATENAY MALABRY CEDEX","zipcode_valid":"92290","city_valid":"CHATENAY MALABRY"}],"92298":[{"city":"CHATENAY MALABRY CEDEX","zipcode_valid":"92290","city_valid":"CHATENAY MALABRY"}],"92299":[{"city":"CHATENAY MALABRY CEDEX","zipcode_valid":"92290","city_valid":"CHATENAY MALABRY"}],"92301":[{"city":"LEVALLOIS PERRET CEDEX","zipcode_valid":"92300","city_valid":"LEVALLOIS PERRET"}],"92302":[{"city":"LEVALLOIS PERRET CEDEX","zipcode_valid":"92300","city_valid":"LEVALLOIS PERRET"}],"92303":[{"city":"LEVALLOIS PERRET CEDEX","zipcode_valid":"92300","city_valid":"LEVALLOIS PERRET"}],"92304":[{"city":"LEVALLOIS PERRET CEDEX","zipcode_valid":"92300","city_valid":"LEVALLOIS PERRET"}],"92305":[{"city":"LEVALLOIS PERRET CEDEX","zipcode_valid":"92300","city_valid":"LEVALLOIS PERRET"}],"92306":[{"city":"LEVALLOIS PERRET CEDEX","zipcode_valid":"92300","city_valid":"LEVALLOIS PERRET"}],"92307":[{"city":"LEVALLOIS PERRET CEDEX","zipcode_valid":"92300","city_valid":"LEVALLOIS PERRET"}],"92308":[{"city":"LEVALLOIS PERRET CEDEX","zipcode_valid":"92300","city_valid":"LEVALLOIS PERRET"}],"92309":[{"city":"LEVALLOIS PERRET CEDEX","zipcode_valid":"92300","city_valid":"LEVALLOIS PERRET"}],"92311":[{"city":"SEVRES CEDEX","zipcode_valid":"92310","city_valid":"SEVRES"}],"92312":[{"city":"SEVRES CEDEX","zipcode_valid":"92310","city_valid":"SEVRES"}],"92313":[{"city":"SEVRES CEDEX","zipcode_valid":"92310","city_valid":"SEVRES"}],"92314":[{"city":"SEVRES CEDEX","zipcode_valid":"92310","city_valid":"SEVRES"}],"92315":[{"city":"SEVRES CEDEX","zipcode_valid":"92310","city_valid":"SEVRES"}],"92316":[{"city":"SEVRES CEDEX","zipcode_valid":"92310","city_valid":"SEVRES"}],"92317":[{"city":"SEVRES CEDEX","zipcode_valid":"92310","city_valid":"SEVRES"}],"92318":[{"city":"SEVRES CEDEX","zipcode_valid":"92310","city_valid":"SEVRES"}],"92319":[{"city":"SEVRES CEDEX","zipcode_valid":"92310","city_valid":"SEVRES"}],"92321":[{"city":"CHATILLON CEDEX","zipcode_valid":"92320","city_valid":"CHATILLON"}],"92322":[{"city":"CHATILLON CEDEX","zipcode_valid":"92320","city_valid":"CHATILLON"}],"92323":[{"city":"CHATILLON CEDEX","zipcode_valid":"92320","city_valid":"CHATILLON"}],"92324":[{"city":"CHATILLON CEDEX","zipcode_valid":"92320","city_valid":"CHATILLON"}],"92325":[{"city":"CHATILLON CEDEX","zipcode_valid":"92320","city_valid":"CHATILLON"}],"92326":[{"city":"CHATILLON CEDEX","zipcode_valid":"92320","city_valid":"CHATILLON"}],"92327":[{"city":"CHATILLON CEDEX","zipcode_valid":"92320","city_valid":"CHATILLON"}],"92328":[{"city":"CHATILLON CEDEX","zipcode_valid":"92320","city_valid":"CHATILLON"}],"92329":[{"city":"CHATILLON CEDEX","zipcode_valid":"92320","city_valid":"CHATILLON"}],"92331":[{"city":"SCEAUX CEDEX","zipcode_valid":"92330","city_valid":"SCEAUX"}],"92332":[{"city":"SCEAUX CEDEX","zipcode_valid":"92330","city_valid":"SCEAUX"}],"92333":[{"city":"SCEAUX CEDEX","zipcode_valid":"92330","city_valid":"SCEAUX"}],"92337":[{"city":"SCEAUX CEDEX","zipcode_valid":"92330","city_valid":"SCEAUX"}],"92338":[{"city":"SCEAUX CEDEX","zipcode_valid":"92330","city_valid":"SCEAUX"}],"92339":[{"city":"SCEAUX CEDEX","zipcode_valid":"92330","city_valid":"SCEAUX"}],"92341":[{"city":"BOURG LA REINE CEDEX","zipcode_valid":"92340","city_valid":"BOURG LA REINE"}],"92342":[{"city":"BOURG LA REINE CEDEX","zipcode_valid":"92340","city_valid":"BOURG LA REINE"}],"92343":[{"city":"BOURG LA REINE CEDEX","zipcode_valid":"92340","city_valid":"BOURG LA REINE"}],"92344":[{"city":"BOURG LA REINE CEDEX","zipcode_valid":"92340","city_valid":"BOURG LA REINE"}],"92349":[{"city":"BOURG LA REINE CEDEX","zipcode_valid":"92340","city_valid":"BOURG LA REINE"}],"92351":[{"city":"LE PLESSIS ROBINSON CEDEX","zipcode_valid":"92350","city_valid":"LE PLESSIS ROBINSON"}],"92352":[{"city":"LE PLESSIS ROBINSON CEDEX","zipcode_valid":"92350","city_valid":"LE PLESSIS ROBINSON"}],"92353":[{"city":"LE PLESSIS ROBINSON CEDEX","zipcode_valid":"92350","city_valid":"LE PLESSIS ROBINSON"}],"92354":[{"city":"LE PLESSIS ROBINSON CEDEX","zipcode_valid":"92350","city_valid":"LE PLESSIS ROBINSON"}],"92355":[{"city":"LE PLESSIS ROBINSON CEDEX","zipcode_valid":"92350","city_valid":"LE PLESSIS ROBINSON"}],"92356":[{"city":"LE PLESSIS ROBINSON CEDEX","zipcode_valid":"92350","city_valid":"LE PLESSIS ROBINSON"}],"92357":[{"city":"LE PLESSIS ROBINSON CEDEX","zipcode_valid":"92350","city_valid":"LE PLESSIS ROBINSON"}],"92358":[{"city":"LE PLESSIS ROBINSON CEDEX","zipcode_valid":"92350","city_valid":"LE PLESSIS ROBINSON"}],"92359":[{"city":"LE PLESSIS ROBINSON CEDEX","zipcode_valid":"92350","city_valid":"LE PLESSIS ROBINSON"}],"92361":[{"city":"MEUDON LA FORET CEDEX","zipcode_valid":"92360","city_valid":"MEUDON LA FORET"}],"92362":[{"city":"MEUDON LA FORET CEDEX","zipcode_valid":"92360","city_valid":"MEUDON LA FORET"}],"92363":[{"city":"MEUDON LA FORET CEDEX","zipcode_valid":"92360","city_valid":"MEUDON LA FORET"}],"92364":[{"city":"MEUDON LA FORET CEDEX","zipcode_valid":"92360","city_valid":"MEUDON LA FORET"}],"92365":[{"city":"MEUDON LA FORET CEDEX","zipcode_valid":"92360","city_valid":"MEUDON LA FORET"}],"92366":[{"city":"MEUDON LA FORET CEDEX","zipcode_valid":"92360","city_valid":"MEUDON LA FORET"}],"92367":[{"city":"MEUDON LA FORET CEDEX","zipcode_valid":"92360","city_valid":"MEUDON LA FORET"}],"92369":[{"city":"MEUDON LA FORET CEDEX","zipcode_valid":"92360","city_valid":"MEUDON LA FORET"}],"92371":[{"city":"CHAVILLE CEDEX","zipcode_valid":"92370","city_valid":"CHAVILLE"}],"92372":[{"city":"CHAVILLE CEDEX","zipcode_valid":"92370","city_valid":"CHAVILLE"}],"92373":[{"city":"CHAVILLE CEDEX","zipcode_valid":"92370","city_valid":"CHAVILLE"}],"92379":[{"city":"CHAVILLE CEDEX","zipcode_valid":"92370","city_valid":"CHAVILLE"}],"92387":[{"city":"VILLENEUVE LA GARENNE CEDEX","zipcode_valid":"92390","city_valid":"VILLENEUVE LA GARENNE"}],"92388":[{"city":"VILLENEUVE LA GARENNE CEDEX","zipcode_valid":"92390","city_valid":"VILLENEUVE LA GARENNE"}],"92389":[{"city":"LEVALLOIS PERRET CEDEX","zipcode_valid":"92300","city_valid":"LEVALLOIS PERRET"}],"92391":[{"city":"VILLENEUVE LA GARENNE CEDEX","zipcode_valid":"92390","city_valid":"VILLENEUVE LA GARENNE"}],"92392":[{"city":"VILLENEUVE LA GARENNE CEDEX","zipcode_valid":"92390","city_valid":"VILLENEUVE LA GARENNE"}],"92393":[{"city":"VILLENEUVE LA GARENNE CEDEX","zipcode_valid":"92390","city_valid":"VILLENEUVE LA GARENNE"}],"92394":[{"city":"VILLENEUVE LA GARENNE CEDEX","zipcode_valid":"92390","city_valid":"VILLENEUVE LA GARENNE"}],"92395":[{"city":"VILLENEUVE LA GARENNE CEDEX","zipcode_valid":"92390","city_valid":"VILLENEUVE LA GARENNE"}],"92396":[{"city":"VILLENEUVE LA GARENNE CEDEX","zipcode_valid":"92390","city_valid":"VILLENEUVE LA GARENNE"}],"92397":[{"city":"VILLENEUVE LA GARENNE CEDEX","zipcode_valid":"92390","city_valid":"VILLENEUVE LA GARENNE"}],"92398":[{"city":"VILLENEUVE LA GARENNE CEDEX","zipcode_valid":"92390","city_valid":"VILLENEUVE LA GARENNE"}],"92399":[{"city":"VILLENEUVE LA GARENNE CEDEX","zipcode_valid":"92390","city_valid":"VILLENEUVE LA GARENNE"}],"92401":[{"city":"COURBEVOIE CEDEX","zipcode_valid":"92400","city_valid":"COURBEVOIE"}],"92402":[{"city":"COURBEVOIE CEDEX","zipcode_valid":"92400","city_valid":"COURBEVOIE"}],"92403":[{"city":"COURBEVOIE CEDEX","zipcode_valid":"92400","city_valid":"COURBEVOIE"}],"92404":[{"city":"COURBEVOIE CEDEX","zipcode_valid":"92400","city_valid":"COURBEVOIE"}],"92405":[{"city":"COURBEVOIE CEDEX","zipcode_valid":"92400","city_valid":"COURBEVOIE"}],"92406":[{"city":"COURBEVOIE CEDEX","zipcode_valid":"92400","city_valid":"COURBEVOIE"}],"92407":[{"city":"COURBEVOIE CEDEX","zipcode_valid":"92400","city_valid":"COURBEVOIE"}],"92408":[{"city":"COURBEVOIE CEDEX","zipcode_valid":"92400","city_valid":"COURBEVOIE"}],"92409":[{"city":"COURBEVOIE CEDEX","zipcode_valid":"92400","city_valid":"COURBEVOIE"}],"92411":[{"city":"COURBEVOIE CEDEX","zipcode_valid":"92400","city_valid":"COURBEVOIE"}],"92412":[{"city":"COURBEVOIE CEDEX","zipcode_valid":"92400","city_valid":"COURBEVOIE"}],"92413":[{"city":"COURBEVOIE CEDEX","zipcode_valid":"92400","city_valid":"COURBEVOIE"}],"92414":[{"city":"COURBEVOIE CEDEX","zipcode_valid":"92400","city_valid":"COURBEVOIE"}],"92415":[{"city":"COURBEVOIE CEDEX","zipcode_valid":"92400","city_valid":"COURBEVOIE"}],"92416":[{"city":"COURBEVOIE CEDEX","zipcode_valid":"92400","city_valid":"COURBEVOIE"}],"92417":[{"city":"COURBEVOIE CEDEX","zipcode_valid":"92400","city_valid":"COURBEVOIE"}],"92418":[{"city":"COURBEVOIE CEDEX","zipcode_valid":"92400","city_valid":"COURBEVOIE"}],"92419":[{"city":"COURBEVOIE CEDEX","zipcode_valid":"92400","city_valid":"COURBEVOIE"}],"92422":[{"city":"GARCHES CEDEX","zipcode_valid":"92380","city_valid":"GARCHES"}],"92423":[{"city":"VAUCRESSON CEDEX","zipcode_valid":"92420","city_valid":"VAUCRESSON"}],"92438":[{"city":"CHATILLON CEDEX","zipcode_valid":"92320","city_valid":"CHATILLON"}],"92439":[{"city":"CHATILLON CEDEX","zipcode_valid":"92320","city_valid":"CHATILLON"}],"92441":[{"city":"ISSY LES MOULINEAUX CEDEX","zipcode_valid":"92130","city_valid":"ISSY LES MOULINEAUX"}],"92442":[{"city":"ISSY LES MOULINEAUX CEDEX","zipcode_valid":"92130","city_valid":"ISSY LES MOULINEAUX"}],"92443":[{"city":"ISSY LES MOULINEAUX CEDEX","zipcode_valid":"92130","city_valid":"ISSY LES MOULINEAUX"}],"92444":[{"city":"ISSY LES MOULINEAUX CEDEX","zipcode_valid":"92130","city_valid":"ISSY LES MOULINEAUX"}],"92445":[{"city":"ISSY LES MOULINEAUX CEDEX","zipcode_valid":"92130","city_valid":"ISSY LES MOULINEAUX"}],"92446":[{"city":"ISSY LES MOULINEAUX CEDEX","zipcode_valid":"92130","city_valid":"ISSY LES MOULINEAUX"}],"92447":[{"city":"ISSY LES MOULINEAUX CEDEX","zipcode_valid":"92130","city_valid":"ISSY LES MOULINEAUX"}],"92448":[{"city":"ISSY LES MOULINEAUX CEDEX","zipcode_valid":"92130","city_valid":"ISSY LES MOULINEAUX"}],"92449":[{"city":"ISSY LES MOULINEAUX CEDEX","zipcode_valid":"92130","city_valid":"ISSY LES MOULINEAUX"}],"92451":[{"city":"ISSY LES MOULINEAUX CEDEX","zipcode_valid":"92130","city_valid":"ISSY LES MOULINEAUX"}],"92452":[{"city":"ISSY LES MOULINEAUX CEDEX","zipcode_valid":"92130","city_valid":"ISSY LES MOULINEAUX"}],"92453":[{"city":"ISSY LES MOULINEAUX CEDEX","zipcode_valid":"92130","city_valid":"ISSY LES MOULINEAUX"}],"92454":[{"city":"ISSY LES MOULINEAUX CEDEX","zipcode_valid":"92130","city_valid":"ISSY LES MOULINEAUX"}],"92455":[{"city":"ISSY LES MOULINEAUX CEDEX","zipcode_valid":"92130","city_valid":"ISSY LES MOULINEAUX"}],"92459":[{"city":"ISSY LES MOULINEAUX CEDEX","zipcode_valid":"92130","city_valid":"ISSY LES MOULINEAUX"}],"92491":[{"city":"SEVRES CEDEX","zipcode_valid":"92310","city_valid":"SEVRES"}],"92492":[{"city":"SEVRES CEDEX","zipcode_valid":"92310","city_valid":"SEVRES"}],"92499":[{"city":"PARIS LA DEFENSE CEDEX","zipcode_valid":"92999","city_valid":"PARIS LA DEFENSE"}],"92501":[{"city":"RUEIL MALMAISON CEDEX","zipcode_valid":"92500","city_valid":"RUEIL MALMAISON"}],"92502":[{"city":"RUEIL MALMAISON CEDEX","zipcode_valid":"92500","city_valid":"RUEIL MALMAISON"}],"92503":[{"city":"RUEIL MALMAISON CEDEX","zipcode_valid":"92500","city_valid":"RUEIL MALMAISON"}],"92504":[{"city":"RUEIL MALMAISON CEDEX","zipcode_valid":"92500","city_valid":"RUEIL MALMAISON"}],"92505":[{"city":"RUEIL MALMAISON CEDEX","zipcode_valid":"92500","city_valid":"RUEIL MALMAISON"}],"92506":[{"city":"RUEIL MALMAISON CEDEX","zipcode_valid":"92500","city_valid":"RUEIL MALMAISON"}],"92507":[{"city":"RUEIL MALMAISON CEDEX","zipcode_valid":"92500","city_valid":"RUEIL MALMAISON"}],"92508":[{"city":"RUEIL MALMAISON CEDEX","zipcode_valid":"92500","city_valid":"RUEIL MALMAISON"}],"92509":[{"city":"RUEIL MALMAISON CEDEX","zipcode_valid":"92500","city_valid":"RUEIL MALMAISON"}],"92511":[{"city":"BOULOGNE BILLANCOURT CEDEX","zipcode_valid":"92100","city_valid":"BOULOGNE BILLANCOURT"}],"92512":[{"city":"BOULOGNE BILLANCOURT CEDEX","zipcode_valid":"92100","city_valid":"BOULOGNE BILLANCOURT"}],"92513":[{"city":"BOULOGNE BILLANCOURT CEDEX","zipcode_valid":"92100","city_valid":"BOULOGNE BILLANCOURT"}],"92514":[{"city":"BOULOGNE BILLANCOURT CEDEX","zipcode_valid":"92100","city_valid":"BOULOGNE BILLANCOURT"}],"92515":[{"city":"BOULOGNE BILLANCOURT CEDEX","zipcode_valid":"92100","city_valid":"BOULOGNE BILLANCOURT"}],"92516":[{"city":"BOULOGNE BILLANCOURT CEDEX","zipcode_valid":"92100","city_valid":"BOULOGNE BILLANCOURT"}],"92517":[{"city":"BOULOGNE BILLANCOURT CEDEX","zipcode_valid":"92100","city_valid":"BOULOGNE BILLANCOURT"}],"92518":[{"city":"BOULOGNE BILLANCOURT CEDEX","zipcode_valid":"92100","city_valid":"BOULOGNE BILLANCOURT"}],"92519":[{"city":"BOULOGNE BILLANCOURT CEDEX","zipcode_valid":"92100","city_valid":"BOULOGNE BILLANCOURT"}],"92521":[{"city":"NEUILLY SUR SEINE CEDEX","zipcode_valid":"92200","city_valid":"NEUILLY SUR SEINE"}],"92522":[{"city":"NEUILLY SUR SEINE CEDEX","zipcode_valid":"92200","city_valid":"NEUILLY SUR SEINE"}],"92523":[{"city":"NEUILLY SUR SEINE CEDEX","zipcode_valid":"92200","city_valid":"NEUILLY SUR SEINE"}],"92524":[{"city":"NEUILLY SUR SEINE CEDEX","zipcode_valid":"92200","city_valid":"NEUILLY SUR SEINE"}],"92525":[{"city":"NEUILLY SUR SEINE CEDEX","zipcode_valid":"92200","city_valid":"NEUILLY SUR SEINE"}],"92526":[{"city":"NEUILLY SUR SEINE CEDEX","zipcode_valid":"92200","city_valid":"NEUILLY SUR SEINE"}],"92527":[{"city":"NEUILLY SUR SEINE CEDEX","zipcode_valid":"92200","city_valid":"NEUILLY SUR SEINE"}],"92528":[{"city":"NEUILLY SUR SEINE CEDEX","zipcode_valid":"92200","city_valid":"NEUILLY SUR SEINE"}],"92529":[{"city":"NEUILLY SUR SEINE CEDEX","zipcode_valid":"92200","city_valid":"NEUILLY SUR SEINE"}],"92531":[{"city":"LEVALLOIS PERRET CEDEX","zipcode_valid":"92300","city_valid":"LEVALLOIS PERRET"}],"92532":[{"city":"LEVALLOIS PERRET CEDEX","zipcode_valid":"92300","city_valid":"LEVALLOIS PERRET"}],"92533":[{"city":"LEVALLOIS PERRET CEDEX","zipcode_valid":"92300","city_valid":"LEVALLOIS PERRET"}],"92534":[{"city":"LEVALLOIS PERRET CEDEX","zipcode_valid":"92300","city_valid":"LEVALLOIS PERRET"}],"92535":[{"city":"LEVALLOIS PERRET CEDEX","zipcode_valid":"92300","city_valid":"LEVALLOIS PERRET"}],"92536":[{"city":"LEVALLOIS PERRET CEDEX","zipcode_valid":"92300","city_valid":"LEVALLOIS PERRET"}],"92537":[{"city":"LEVALLOIS PERRET CEDEX","zipcode_valid":"92300","city_valid":"LEVALLOIS PERRET"}],"92538":[{"city":"LEVALLOIS PERRET CEDEX","zipcode_valid":"92300","city_valid":"LEVALLOIS PERRET"}],"92539":[{"city":"LEVALLOIS PERRET CEDEX","zipcode_valid":"92300","city_valid":"LEVALLOIS PERRET"}],"92541":[{"city":"MONTROUGE CEDEX","zipcode_valid":"92120","city_valid":"MONTROUGE"}],"92542":[{"city":"MONTROUGE CEDEX","zipcode_valid":"92120","city_valid":"MONTROUGE"}],"92543":[{"city":"MONTROUGE CEDEX","zipcode_valid":"92120","city_valid":"MONTROUGE"}],"92544":[{"city":"MONTROUGE CEDEX","zipcode_valid":"92120","city_valid":"MONTROUGE"}],"92545":[{"city":"MONTROUGE CEDEX","zipcode_valid":"92120","city_valid":"MONTROUGE"}],"92546":[{"city":"MONTROUGE CEDEX","zipcode_valid":"92120","city_valid":"MONTROUGE"}],"92547":[{"city":"MONTROUGE CEDEX","zipcode_valid":"92120","city_valid":"MONTROUGE"}],"92548":[{"city":"MONTROUGE CEDEX","zipcode_valid":"92120","city_valid":"MONTROUGE"}],"92549":[{"city":"MONTROUGE CEDEX","zipcode_valid":"92120","city_valid":"MONTROUGE"}],"92551":[{"city":"ST CLOUD CEDEX","zipcode_valid":"92210","city_valid":"ST CLOUD"}],"92552":[{"city":"ST CLOUD CEDEX","zipcode_valid":"92210","city_valid":"ST CLOUD"}],"92553":[{"city":"ST CLOUD CEDEX","zipcode_valid":"92210","city_valid":"ST CLOUD"}],"92554":[{"city":"ST CLOUD CEDEX","zipcode_valid":"92210","city_valid":"ST CLOUD"}],"92555":[{"city":"ST CLOUD CEDEX","zipcode_valid":"92210","city_valid":"ST CLOUD"}],"92561":[{"city":"RUEIL MALMAISON CEDEX","zipcode_valid":"92500","city_valid":"RUEIL MALMAISON"}],"92562":[{"city":"RUEIL MALMAISON CEDEX","zipcode_valid":"92500","city_valid":"RUEIL MALMAISON"}],"92563":[{"city":"RUEIL MALMAISON CEDEX","zipcode_valid":"92500","city_valid":"RUEIL MALMAISON"}],"92564":[{"city":"RUEIL MALMAISON CEDEX","zipcode_valid":"92500","city_valid":"RUEIL MALMAISON"}],"92565":[{"city":"RUEIL MALMAISON CEDEX","zipcode_valid":"92500","city_valid":"RUEIL MALMAISON"}],"92566":[{"city":"RUEIL MALMAISON CEDEX","zipcode_valid":"92500","city_valid":"RUEIL MALMAISON"}],"92567":[{"city":"RUEIL MALMAISON CEDEX","zipcode_valid":"92500","city_valid":"RUEIL MALMAISON"}],"92568":[{"city":"RUEIL MALMAISON CEDEX","zipcode_valid":"92500","city_valid":"RUEIL MALMAISON"}],"92569":[{"city":"RUEIL MALMAISON CEDEX","zipcode_valid":"92500","city_valid":"RUEIL MALMAISON"}],"92571":[{"city":"NEUILLY SUR SEINE CEDEX","zipcode_valid":"92200","city_valid":"NEUILLY SUR SEINE"}],"92572":[{"city":"NEUILLY SUR SEINE CEDEX","zipcode_valid":"92200","city_valid":"NEUILLY SUR SEINE"}],"92573":[{"city":"NEUILLY SUR SEINE CEDEX","zipcode_valid":"92200","city_valid":"NEUILLY SUR SEINE"}],"92574":[{"city":"NEUILLY SUR SEINE CEDEX","zipcode_valid":"92200","city_valid":"NEUILLY SUR SEINE"}],"92575":[{"city":"NEUILLY SUR SEINE CEDEX","zipcode_valid":"92200","city_valid":"NEUILLY SUR SEINE"}],"92576":[{"city":"NEUILLY SUR SEINE CEDEX","zipcode_valid":"92200","city_valid":"NEUILLY SUR SEINE"}],"92577":[{"city":"NEUILLY SUR SEINE CEDEX","zipcode_valid":"92200","city_valid":"NEUILLY SUR SEINE"}],"92578":[{"city":"NEUILLY SUR SEINE CEDEX","zipcode_valid":"92200","city_valid":"NEUILLY SUR SEINE"}],"92579":[{"city":"NEUILLY SUR SEINE CEDEX","zipcode_valid":"92200","city_valid":"NEUILLY SUR SEINE"}],"92581":[{"city":"CLICHY CEDEX","zipcode_valid":"92110","city_valid":"CLICHY"}],"92582":[{"city":"CLICHY CEDEX","zipcode_valid":"92110","city_valid":"CLICHY"}],"92583":[{"city":"CLICHY CEDEX","zipcode_valid":"92110","city_valid":"CLICHY"}],"92584":[{"city":"CLICHY CEDEX","zipcode_valid":"92110","city_valid":"CLICHY"}],"92585":[{"city":"CLICHY CEDEX","zipcode_valid":"92110","city_valid":"CLICHY"}],"92586":[{"city":"CLICHY CEDEX","zipcode_valid":"92110","city_valid":"CLICHY"}],"92587":[{"city":"CLICHY CEDEX","zipcode_valid":"92110","city_valid":"CLICHY"}],"92588":[{"city":"CLICHY CEDEX","zipcode_valid":"92110","city_valid":"CLICHY"}],"92589":[{"city":"CLICHY CEDEX","zipcode_valid":"92110","city_valid":"CLICHY"}],"92591":[{"city":"LEVALLOIS PERRET CEDEX","zipcode_valid":"92300","city_valid":"LEVALLOIS PERRET"}],"92592":[{"city":"LEVALLOIS PERRET CEDEX","zipcode_valid":"92300","city_valid":"LEVALLOIS PERRET"}],"92593":[{"city":"LEVALLOIS PERRET CEDEX","zipcode_valid":"92300","city_valid":"LEVALLOIS PERRET"}],"92594":[{"city":"LEVALLOIS PERRET CEDEX","zipcode_valid":"92300","city_valid":"LEVALLOIS PERRET"}],"92595":[{"city":"LEVALLOIS PERRET CEDEX","zipcode_valid":"92300","city_valid":"LEVALLOIS PERRET"}],"92596":[{"city":"LEVALLOIS PERRET CEDEX","zipcode_valid":"92300","city_valid":"LEVALLOIS PERRET"}],"92597":[{"city":"LEVALLOIS PERRET CEDEX","zipcode_valid":"92300","city_valid":"LEVALLOIS PERRET"}],"92598":[{"city":"LEVALLOIS PERRET CEDEX","zipcode_valid":"92300","city_valid":"LEVALLOIS PERRET"}],"92599":[{"city":"LEVALLOIS PERRET CEDEX","zipcode_valid":"92300","city_valid":"LEVALLOIS PERRET"}],"92601":[{"city":"ASNIERES SUR SEINE CEDEX","zipcode_valid":"92600","city_valid":"ASNIERES SUR SEINE"}],"92602":[{"city":"ASNIERES SUR SEINE CEDEX","zipcode_valid":"92600","city_valid":"ASNIERES SUR SEINE"}],"92603":[{"city":"ASNIERES SUR SEINE CEDEX","zipcode_valid":"92600","city_valid":"ASNIERES SUR SEINE"}],"92604":[{"city":"ASNIERES SUR SEINE CEDEX","zipcode_valid":"92600","city_valid":"ASNIERES SUR SEINE"}],"92605":[{"city":"ASNIERES SUR SEINE CEDEX","zipcode_valid":"92600","city_valid":"ASNIERES SUR SEINE"}],"92606":[{"city":"ASNIERES SUR SEINE CEDEX","zipcode_valid":"92600","city_valid":"ASNIERES SUR SEINE"}],"92607":[{"city":"ASNIERES SUR SEINE CEDEX","zipcode_valid":"92600","city_valid":"ASNIERES SUR SEINE"}],"92608":[{"city":"ASNIERES SUR SEINE CEDEX","zipcode_valid":"92600","city_valid":"ASNIERES SUR SEINE"}],"92609":[{"city":"ASNIERES SUR SEINE CEDEX","zipcode_valid":"92600","city_valid":"ASNIERES SUR SEINE"}],"92611":[{"city":"CLICHY CEDEX","zipcode_valid":"92110","city_valid":"CLICHY"}],"92612":[{"city":"CLICHY CEDEX","zipcode_valid":"92110","city_valid":"CLICHY"}],"92613":[{"city":"CLICHY CEDEX","zipcode_valid":"92110","city_valid":"CLICHY"}],"92614":[{"city":"CLICHY CEDEX","zipcode_valid":"92110","city_valid":"CLICHY"}],"92615":[{"city":"CLICHY CEDEX","zipcode_valid":"92110","city_valid":"CLICHY"}],"92616":[{"city":"CLICHY CEDEX","zipcode_valid":"92110","city_valid":"CLICHY"}],"92621":[{"city":"GENNEVILLIERS CEDEX","zipcode_valid":"92230","city_valid":"GENNEVILLIERS"}],"92622":[{"city":"GENNEVILLIERS CEDEX","zipcode_valid":"92230","city_valid":"GENNEVILLIERS"}],"92623":[{"city":"GENNEVILLIERS CEDEX","zipcode_valid":"92230","city_valid":"GENNEVILLIERS"}],"92624":[{"city":"GENNEVILLIERS CEDEX","zipcode_valid":"92230","city_valid":"GENNEVILLIERS"}],"92625":[{"city":"GENNEVILLIERS CEDEX","zipcode_valid":"92230","city_valid":"GENNEVILLIERS"}],"92626":[{"city":"GENNEVILLIERS CEDEX","zipcode_valid":"92230","city_valid":"GENNEVILLIERS"}],"92631":[{"city":"GENNEVILLIERS CEDEX","zipcode_valid":"92230","city_valid":"GENNEVILLIERS"}],"92632":[{"city":"GENNEVILLIERS CEDEX","zipcode_valid":"92230","city_valid":"GENNEVILLIERS"}],"92633":[{"city":"GENNEVILLIERS CEDEX","zipcode_valid":"92230","city_valid":"GENNEVILLIERS"}],"92634":[{"city":"GENNEVILLIERS CEDEX","zipcode_valid":"92230","city_valid":"GENNEVILLIERS"}],"92635":[{"city":"GENNEVILLIERS CEDEX","zipcode_valid":"92230","city_valid":"GENNEVILLIERS"}],"92636":[{"city":"GENNEVILLIERS CEDEX","zipcode_valid":"92230","city_valid":"GENNEVILLIERS"}],"92637":[{"city":"GENNEVILLIERS CEDEX","zipcode_valid":"92230","city_valid":"GENNEVILLIERS"}],"92638":[{"city":"GENNEVILLIERS CEDEX","zipcode_valid":"92230","city_valid":"GENNEVILLIERS"}],"92640":[{"city":"BOULOGNE BILLANCOURT CEDEX","zipcode_valid":"92100","city_valid":"BOULOGNE BILLANCOURT"}],"92641":[{"city":"BOULOGNE BILLANCOURT CEDEX","zipcode_valid":"92100","city_valid":"BOULOGNE BILLANCOURT"}],"92642":[{"city":"BOULOGNE BILLANCOURT CEDEX","zipcode_valid":"92100","city_valid":"BOULOGNE BILLANCOURT"}],"92643":[{"city":"BOULOGNE BILLANCOURT CEDEX","zipcode_valid":"92100","city_valid":"BOULOGNE BILLANCOURT"}],"92644":[{"city":"BOULOGNE BILLANCOURT CEDEX","zipcode_valid":"92100","city_valid":"BOULOGNE BILLANCOURT"}],"92645":[{"city":"BOULOGNE BILLANCOURT CEDEX","zipcode_valid":"92100","city_valid":"BOULOGNE BILLANCOURT"}],"92646":[{"city":"BOULOGNE BILLANCOURT CEDEX","zipcode_valid":"92100","city_valid":"BOULOGNE BILLANCOURT"}],"92648":[{"city":"BOULOGNE BILLANCOURT CEDEX","zipcode_valid":"92100","city_valid":"BOULOGNE BILLANCOURT"}],"92649":[{"city":"BOULOGNE BILLANCOURT CEDEX","zipcode_valid":"92100","city_valid":"BOULOGNE BILLANCOURT"}],"92650":[{"city":"BOULOGNE BILLANCOURT CEDEX","zipcode_valid":"92100","city_valid":"BOULOGNE BILLANCOURT"}],"92651":[{"city":"BOULOGNE BILLANCOURT CEDEX","zipcode_valid":"92100","city_valid":"BOULOGNE BILLANCOURT"}],"92652":[{"city":"BOULOGNE BILLANCOURT CEDEX","zipcode_valid":"92100","city_valid":"BOULOGNE BILLANCOURT"}],"92653":[{"city":"BOULOGNE BILLANCOURT CEDEX","zipcode_valid":"92100","city_valid":"BOULOGNE BILLANCOURT"}],"92654":[{"city":"BOULOGNE BILLANCOURT CEDEX","zipcode_valid":"92100","city_valid":"BOULOGNE BILLANCOURT"}],"92655":[{"city":"BOULOGNE BILLANCOURT CEDEX","zipcode_valid":"92100","city_valid":"BOULOGNE BILLANCOURT"}],"92656":[{"city":"BOULOGNE BILLANCOURT CEDEX","zipcode_valid":"92100","city_valid":"BOULOGNE BILLANCOURT"}],"92657":[{"city":"BOULOGNE BILLANCOURT CEDEX","zipcode_valid":"92100","city_valid":"BOULOGNE BILLANCOURT"}],"92658":[{"city":"BOULOGNE BILLANCOURT CEDEX","zipcode_valid":"92100","city_valid":"BOULOGNE BILLANCOURT"}],"92659":[{"city":"BOULOGNE BILLANCOURT CEDEX","zipcode_valid":"92100","city_valid":"BOULOGNE BILLANCOURT"}],"92660":[{"city":"BOULOGNE BILLANCOURT CEDEX","zipcode_valid":"92100","city_valid":"BOULOGNE BILLANCOURT"}],"92661":[{"city":"ASNIERES SUR SEINE CEDEX","zipcode_valid":"92600","city_valid":"ASNIERES SUR SEINE"}],"92662":[{"city":"ASNIERES SUR SEINE CEDEX","zipcode_valid":"92600","city_valid":"ASNIERES SUR SEINE"}],"92665":[{"city":"ASNIERES SUR SEINE CEDEX","zipcode_valid":"92600","city_valid":"ASNIERES SUR SEINE"}],"92666":[{"city":"ASNIERES SUR SEINE CEDEX","zipcode_valid":"92600","city_valid":"ASNIERES SUR SEINE"}],"92667":[{"city":"ASNIERES SUR SEINE CEDEX","zipcode_valid":"92600","city_valid":"ASNIERES SUR SEINE"}],"92671":[{"city":"COURBEVOIE CEDEX","zipcode_valid":"92400","city_valid":"COURBEVOIE"}],"92672":[{"city":"COURBEVOIE CEDEX","zipcode_valid":"92400","city_valid":"COURBEVOIE"}],"92675":[{"city":"COURBEVOIE CEDEX","zipcode_valid":"92400","city_valid":"COURBEVOIE"}],"92677":[{"city":"COURBEVOIE CEDEX","zipcode_valid":"92400","city_valid":"COURBEVOIE"}],"92679":[{"city":"COURBEVOIE CEDEX","zipcode_valid":"92400","city_valid":"COURBEVOIE"}],"92681":[{"city":"LEVALLOIS PERRET CEDEX","zipcode_valid":"92300","city_valid":"LEVALLOIS PERRET"}],"92682":[{"city":"LEVALLOIS PERRET CEDEX","zipcode_valid":"92300","city_valid":"LEVALLOIS PERRET"}],"92683":[{"city":"LEVALLOIS PERRET CEDEX","zipcode_valid":"92300","city_valid":"LEVALLOIS PERRET"}],"92684":[{"city":"LEVALLOIS PERRET CEDEX","zipcode_valid":"92300","city_valid":"LEVALLOIS PERRET"}],"92685":[{"city":"LEVALLOIS PERRET CEDEX","zipcode_valid":"92300","city_valid":"LEVALLOIS PERRET"}],"92686":[{"city":"LEVALLOIS PERRET CEDEX","zipcode_valid":"92300","city_valid":"LEVALLOIS PERRET"}],"92687":[{"city":"LEVALLOIS PERRET CEDEX","zipcode_valid":"92300","city_valid":"LEVALLOIS PERRET"}],"92688":[{"city":"LEVALLOIS PERRET CEDEX","zipcode_valid":"92300","city_valid":"LEVALLOIS PERRET"}],"92689":[{"city":"LEVALLOIS PERRET CEDEX","zipcode_valid":"92300","city_valid":"LEVALLOIS PERRET"}],"92691":[{"city":"LEVALLOIS PERRET CEDEX","zipcode_valid":"92300","city_valid":"LEVALLOIS PERRET"}],"92692":[{"city":"COURBEVOIE CEDEX","zipcode_valid":"92400","city_valid":"COURBEVOIE"}],"92693":[{"city":"LEVALLOIS PERRET CEDEX","zipcode_valid":"92300","city_valid":"LEVALLOIS PERRET"}],"92695":[{"city":"LEVALLOIS PERRET CEDEX","zipcode_valid":"92300","city_valid":"LEVALLOIS PERRET"}],"92697":[{"city":"LEVALLOIS PERRET CEDEX","zipcode_valid":"92300","city_valid":"LEVALLOIS PERRET"}],"92698":[{"city":"LEVALLOIS PERRET CEDEX","zipcode_valid":"92300","city_valid":"LEVALLOIS PERRET"}],"92701":[{"city":"COLOMBES CEDEX","zipcode_valid":"92700","city_valid":"COLOMBES"}],"92702":[{"city":"COLOMBES CEDEX","zipcode_valid":"92700","city_valid":"COLOMBES"}],"92703":[{"city":"COLOMBES CEDEX","zipcode_valid":"92700","city_valid":"COLOMBES"}],"92704":[{"city":"COLOMBES CEDEX","zipcode_valid":"92700","city_valid":"COLOMBES"}],"92705":[{"city":"COLOMBES CEDEX","zipcode_valid":"92700","city_valid":"COLOMBES"}],"92706":[{"city":"COLOMBES CEDEX","zipcode_valid":"92700","city_valid":"COLOMBES"}],"92707":[{"city":"COLOMBES CEDEX","zipcode_valid":"92700","city_valid":"COLOMBES"}],"92708":[{"city":"COLOMBES CEDEX","zipcode_valid":"92700","city_valid":"COLOMBES"}],"92709":[{"city":"COLOMBES CEDEX","zipcode_valid":"92700","city_valid":"COLOMBES"}],"92711":[{"city":"COLOMBES CEDEX","zipcode_valid":"92700","city_valid":"COLOMBES"}],"92712":[{"city":"COLOMBES CEDEX","zipcode_valid":"92700","city_valid":"COLOMBES"}],"92713":[{"city":"COLOMBES CEDEX","zipcode_valid":"92700","city_valid":"COLOMBES"}],"92714":[{"city":"COLOMBES CEDEX","zipcode_valid":"92700","city_valid":"COLOMBES"}],"92715":[{"city":"COLOMBES CEDEX","zipcode_valid":"92700","city_valid":"COLOMBES"}],"92716":[{"city":"COLOMBES CEDEX","zipcode_valid":"92700","city_valid":"COLOMBES"}],"92717":[{"city":"COLOMBES CEDEX","zipcode_valid":"92700","city_valid":"COLOMBES"}],"92718":[{"city":"COLOMBES CEDEX","zipcode_valid":"92700","city_valid":"COLOMBES"}],"92719":[{"city":"COLOMBES CEDEX","zipcode_valid":"92700","city_valid":"COLOMBES"}],"92721":[{"city":"NANTERRE CEDEX","zipcode_valid":"92000","city_valid":"NANTERRE"}],"92722":[{"city":"NANTERRE CEDEX","zipcode_valid":"92000","city_valid":"NANTERRE"}],"92723":[{"city":"NANTERRE CEDEX","zipcode_valid":"92000","city_valid":"NANTERRE"}],"92724":[{"city":"NANTERRE CEDEX","zipcode_valid":"92000","city_valid":"NANTERRE"}],"92725":[{"city":"NANTERRE CEDEX","zipcode_valid":"92000","city_valid":"NANTERRE"}],"92726":[{"city":"NANTERRE CEDEX","zipcode_valid":"92000","city_valid":"NANTERRE"}],"92727":[{"city":"NANTERRE CEDEX","zipcode_valid":"92000","city_valid":"NANTERRE"}],"92728":[{"city":"NANTERRE CEDEX","zipcode_valid":"92000","city_valid":"NANTERRE"}],"92729":[{"city":"NANTERRE CEDEX","zipcode_valid":"92000","city_valid":"NANTERRE"}],"92730":[{"city":"NANTERRE CEDEX","zipcode_valid":"92000","city_valid":"NANTERRE"}],"92731":[{"city":"NANTERRE CEDEX","zipcode_valid":"92000","city_valid":"NANTERRE"}],"92733":[{"city":"NANTERRE CEDEX","zipcode_valid":"92000","city_valid":"NANTERRE"}],"92734":[{"city":"NANTERRE CEDEX","zipcode_valid":"92000","city_valid":"NANTERRE"}],"92735":[{"city":"NANTERRE CEDEX","zipcode_valid":"92000","city_valid":"NANTERRE"}],"92736":[{"city":"NANTERRE CEDEX","zipcode_valid":"92000","city_valid":"NANTERRE"}],"92737":[{"city":"NANTERRE CEDEX","zipcode_valid":"92000","city_valid":"NANTERRE"}],"92738":[{"city":"NANTERRE CEDEX","zipcode_valid":"92000","city_valid":"NANTERRE"}],"92739":[{"city":"NANTERRE CEDEX","zipcode_valid":"92000","city_valid":"NANTERRE"}],"92741":[{"city":"NANTERRE CEDEX","zipcode_valid":"92000","city_valid":"NANTERRE"}],"92742":[{"city":"NANTERRE CEDEX","zipcode_valid":"92000","city_valid":"NANTERRE"}],"92743":[{"city":"NANTERRE CEDEX","zipcode_valid":"92000","city_valid":"NANTERRE"}],"92744":[{"city":"NANTERRE CEDEX","zipcode_valid":"92000","city_valid":"NANTERRE"}],"92745":[{"city":"NANTERRE CEDEX","zipcode_valid":"92000","city_valid":"NANTERRE"}],"92746":[{"city":"NANTERRE CEDEX","zipcode_valid":"92000","city_valid":"NANTERRE"}],"92747":[{"city":"NANTERRE CEDEX","zipcode_valid":"92000","city_valid":"NANTERRE"}],"92748":[{"city":"NANTERRE CEDEX","zipcode_valid":"92000","city_valid":"NANTERRE"}],"92751":[{"city":"NANTERRE CEDEX","zipcode_valid":"92000","city_valid":"NANTERRE"}],"92752":[{"city":"NANTERRE CEDEX","zipcode_valid":"92000","city_valid":"NANTERRE"}],"92754":[{"city":"NANTERRE CEDEX","zipcode_valid":"92000","city_valid":"NANTERRE"}],"92755":[{"city":"NANTERRE CEDEX","zipcode_valid":"92000","city_valid":"NANTERRE"}],"92756":[{"city":"NANTERRE CEDEX","zipcode_valid":"92000","city_valid":"NANTERRE"}],"92757":[{"city":"NANTERRE CEDEX","zipcode_valid":"92000","city_valid":"NANTERRE"}],"92758":[{"city":"NANTERRE CEDEX","zipcode_valid":"92000","city_valid":"NANTERRE"}],"92761":[{"city":"ANTONY CEDEX","zipcode_valid":"92160","city_valid":"ANTONY"}],"92762":[{"city":"ANTONY CEDEX","zipcode_valid":"92160","city_valid":"ANTONY"}],"92763":[{"city":"ANTONY CEDEX","zipcode_valid":"92160","city_valid":"ANTONY"}],"92764":[{"city":"ANTONY CEDEX","zipcode_valid":"92160","city_valid":"ANTONY"}],"92765":[{"city":"ANTONY CEDEX","zipcode_valid":"92160","city_valid":"ANTONY"}],"92766":[{"city":"ANTONY CEDEX","zipcode_valid":"92160","city_valid":"ANTONY"}],"92767":[{"city":"ANTONY CEDEX","zipcode_valid":"92160","city_valid":"ANTONY"}],"92768":[{"city":"ANTONY CEDEX","zipcode_valid":"92160","city_valid":"ANTONY"}],"92769":[{"city":"ANTONY CEDEX","zipcode_valid":"92160","city_valid":"ANTONY"}],"92771":[{"city":"BOULOGNE BILLANCOURT CEDEX","zipcode_valid":"92100","city_valid":"BOULOGNE BILLANCOURT"}],"92772":[{"city":"BOULOGNE BILLANCOURT CEDEX","zipcode_valid":"92100","city_valid":"BOULOGNE BILLANCOURT"}],"92773":[{"city":"BOULOGNE BILLANCOURT CEDEX","zipcode_valid":"92100","city_valid":"BOULOGNE BILLANCOURT"}],"92774":[{"city":"BOULOGNE BILLANCOURT CEDEX","zipcode_valid":"92100","city_valid":"BOULOGNE BILLANCOURT"}],"92775":[{"city":"BOULOGNE BILLANCOURT CEDEX","zipcode_valid":"92100","city_valid":"BOULOGNE BILLANCOURT"}],"92776":[{"city":"BOULOGNE BILLANCOURT CEDEX","zipcode_valid":"92100","city_valid":"BOULOGNE BILLANCOURT"}],"92777":[{"city":"BOULOGNE BILLANCOURT CEDEX","zipcode_valid":"92100","city_valid":"BOULOGNE BILLANCOURT"}],"92778":[{"city":"BOULOGNE BILLANCOURT CEDEX","zipcode_valid":"92100","city_valid":"BOULOGNE BILLANCOURT"}],"92779":[{"city":"BOULOGNE BILLANCOURT CEDEX","zipcode_valid":"92100","city_valid":"BOULOGNE BILLANCOURT"}],"92781":[{"city":"ISSY LES MOULINEAUX CEDEX 9","zipcode_valid":"92130","city_valid":"ISSY LES MOULINEAUX"}],"92782":[{"city":"ISSY LES MOULINEAUX CEDEX 9","zipcode_valid":"92130","city_valid":"ISSY LES MOULINEAUX"}],"92783":[{"city":"ISSY LES MOULINEAUX CEDEX 9","zipcode_valid":"92130","city_valid":"ISSY LES MOULINEAUX"}],"92784":[{"city":"ISSY LES MOULINEAUX CEDEX 9","zipcode_valid":"92130","city_valid":"ISSY LES MOULINEAUX"}],"92785":[{"city":"ISSY LES MOULINEAUX CEDEX 9","zipcode_valid":"92130","city_valid":"ISSY LES MOULINEAUX"}],"92786":[{"city":"ISSY LES MOULINEAUX CEDEX 9","zipcode_valid":"92130","city_valid":"ISSY LES MOULINEAUX"}],"92787":[{"city":"ISSY LES MOULINEAUX CEDEX 9","zipcode_valid":"92130","city_valid":"ISSY LES MOULINEAUX"}],"92788":[{"city":"ISSY LES MOULINEAUX CEDEX 9","zipcode_valid":"92130","city_valid":"ISSY LES MOULINEAUX"}],"92789":[{"city":"ISSY LES MOULINEAUX CEDEX 9","zipcode_valid":"92130","city_valid":"ISSY LES MOULINEAUX"}],"92791":[{"city":"ISSY LES MOULINEAUX CEDEX 9","zipcode_valid":"92130","city_valid":"ISSY LES MOULINEAUX"}],"92792":[{"city":"ISSY LES MOULINEAUX CEDEX 9","zipcode_valid":"92130","city_valid":"ISSY LES MOULINEAUX"}],"92793":[{"city":"ISSY LES MOULINEAUX CEDEX 9","zipcode_valid":"92130","city_valid":"ISSY LES MOULINEAUX"}],"92794":[{"city":"ISSY LES MOULINEAUX CEDEX 9","zipcode_valid":"92130","city_valid":"ISSY LES MOULINEAUX"}],"92795":[{"city":"ISSY LES MOULINEAUX CEDEX 9","zipcode_valid":"92130","city_valid":"ISSY LES MOULINEAUX"}],"92796":[{"city":"ISSY LES MOULINEAUX CEDEX 9","zipcode_valid":"92130","city_valid":"ISSY LES MOULINEAUX"}],"92797":[{"city":"ISSY LES MOULINEAUX CEDEX 9","zipcode_valid":"92130","city_valid":"ISSY LES MOULINEAUX"}],"92798":[{"city":"ISSY LES MOULINEAUX CEDEX 9","zipcode_valid":"92130","city_valid":"ISSY LES MOULINEAUX"}],"92799":[{"city":"ISSY LES MOULINEAUX CEDEX 9","zipcode_valid":"92130","city_valid":"ISSY LES MOULINEAUX"}],"92801":[{"city":"PUTEAUX CEDEX","zipcode_valid":"92800","city_valid":"PUTEAUX"}],"92802":[{"city":"PUTEAUX CEDEX","zipcode_valid":"92800","city_valid":"PUTEAUX"}],"92803":[{"city":"PUTEAUX CEDEX","zipcode_valid":"92800","city_valid":"PUTEAUX"}],"92804":[{"city":"PUTEAUX CEDEX","zipcode_valid":"92800","city_valid":"PUTEAUX"}],"92805":[{"city":"PUTEAUX CEDEX","zipcode_valid":"92800","city_valid":"PUTEAUX"}],"92806":[{"city":"PUTEAUX CEDEX","zipcode_valid":"92800","city_valid":"PUTEAUX"}],"92807":[{"city":"PUTEAUX CEDEX","zipcode_valid":"92800","city_valid":"PUTEAUX"}],"92808":[{"city":"PUTEAUX CEDEX","zipcode_valid":"92800","city_valid":"PUTEAUX"}],"92809":[{"city":"PUTEAUX CEDEX","zipcode_valid":"92800","city_valid":"PUTEAUX"}],"92811":[{"city":"PUTEAUX CEDEX","zipcode_valid":"92800","city_valid":"PUTEAUX"}],"92812":[{"city":"PUTEAUX CEDEX","zipcode_valid":"92800","city_valid":"PUTEAUX"}],"92813":[{"city":"PUTEAUX CEDEX","zipcode_valid":"92800","city_valid":"PUTEAUX"}],"92814":[{"city":"PUTEAUX CEDEX","zipcode_valid":"92800","city_valid":"PUTEAUX"}],"92815":[{"city":"PUTEAUX CEDEX","zipcode_valid":"92800","city_valid":"PUTEAUX"}],"92816":[{"city":"PUTEAUX CEDEX","zipcode_valid":"92800","city_valid":"PUTEAUX"}],"92817":[{"city":"PUTEAUX CEDEX","zipcode_valid":"92800","city_valid":"PUTEAUX"}],"92818":[{"city":"PUTEAUX CEDEX","zipcode_valid":"92800","city_valid":"PUTEAUX"}],"92819":[{"city":"PUTEAUX CEDEX","zipcode_valid":"92800","city_valid":"PUTEAUX"}],"92820":[{"city":"PUTEAUX CEDEX","zipcode_valid":"92800","city_valid":"PUTEAUX"}],"92821":[{"city":"PUTEAUX CEDEX","zipcode_valid":"92800","city_valid":"PUTEAUX"}],"92822":[{"city":"PUTEAUX CEDEX","zipcode_valid":"92800","city_valid":"PUTEAUX"}],"92823":[{"city":"PUTEAUX CEDEX","zipcode_valid":"92800","city_valid":"PUTEAUX"}],"92824":[{"city":"PUTEAUX CEDEX","zipcode_valid":"92800","city_valid":"PUTEAUX"}],"92829":[{"city":"PUTEAUX CEDEX","zipcode_valid":"92800","city_valid":"PUTEAUX"}],"92841":[{"city":"RUEIL MALMAISON CEDEX","zipcode_valid":"92500","city_valid":"RUEIL MALMAISON"}],"92842":[{"city":"RUEIL MALMAISON CEDEX","zipcode_valid":"92500","city_valid":"RUEIL MALMAISON"}],"92843":[{"city":"RUEIL MALMAISON CEDEX","zipcode_valid":"92500","city_valid":"RUEIL MALMAISON"}],"92844":[{"city":"RUEIL MALMAISON CEDEX","zipcode_valid":"92500","city_valid":"RUEIL MALMAISON"}],"92845":[{"city":"RUEIL MALMAISON CEDEX","zipcode_valid":"92500","city_valid":"RUEIL MALMAISON"}],"92846":[{"city":"RUEIL MALMAISON CEDEX","zipcode_valid":"92500","city_valid":"RUEIL MALMAISON"}],"92847":[{"city":"RUEIL MALMAISON CEDEX","zipcode_valid":"92500","city_valid":"RUEIL MALMAISON"}],"92848":[{"city":"RUEIL MALMAISON CEDEX","zipcode_valid":"92500","city_valid":"RUEIL MALMAISON"}],"92849":[{"city":"RUEIL MALMAISON CEDEX","zipcode_valid":"92500","city_valid":"RUEIL MALMAISON"}],"92851":[{"city":"RUEIL MALMAISON CEDEX","zipcode_valid":"92500","city_valid":"RUEIL MALMAISON"}],"92852":[{"city":"RUEIL MALMAISON CEDEX","zipcode_valid":"92500","city_valid":"RUEIL MALMAISON"}],"92853":[{"city":"RUEIL MALMAISON CEDEX","zipcode_valid":"92500","city_valid":"RUEIL MALMAISON"}],"92854":[{"city":"RUEIL MALMAISON CEDEX","zipcode_valid":"92500","city_valid":"RUEIL MALMAISON"}],"92855":[{"city":"RUEIL MALMAISON CEDEX","zipcode_valid":"92500","city_valid":"RUEIL MALMAISON"}],"92856":[{"city":"RUEIL MALMAISON CEDEX","zipcode_valid":"92500","city_valid":"RUEIL MALMAISON"}],"92857":[{"city":"RUEIL MALMAISON CEDEX","zipcode_valid":"92500","city_valid":"RUEIL MALMAISON"}],"92858":[{"city":"RUEIL MALMAISON CEDEX","zipcode_valid":"92500","city_valid":"RUEIL MALMAISON"}],"92859":[{"city":"RUEIL MALMAISON CEDEX","zipcode_valid":"92500","city_valid":"RUEIL MALMAISON"}],"92861":[{"city":"ISSY LES MOULINEAUX CEDEX 9","zipcode_valid":"92130","city_valid":"ISSY LES MOULINEAUX"}],"92862":[{"city":"ISSY LES MOULINEAUX CEDEX 9","zipcode_valid":"92130","city_valid":"ISSY LES MOULINEAUX"}],"92863":[{"city":"ISSY LES MOULINEAUX CEDEX 9","zipcode_valid":"92130","city_valid":"ISSY LES MOULINEAUX"}],"92864":[{"city":"ISSY LES MOULINEAUX CEDEX 9","zipcode_valid":"92130","city_valid":"ISSY LES MOULINEAUX"}],"92865":[{"city":"ISSY LES MOULINEAUX CEDEX 9","zipcode_valid":"92130","city_valid":"ISSY LES MOULINEAUX"}],"92866":[{"city":"ISSY LES MOULINEAUX CEDEX 9","zipcode_valid":"92130","city_valid":"ISSY LES MOULINEAUX"}],"92867":[{"city":"ISSY LES MOULINEAUX CEDEX 9","zipcode_valid":"92130","city_valid":"ISSY LES MOULINEAUX"}],"92881":[{"city":"NANTERRE CEDEX 9","zipcode_valid":"92000","city_valid":"NANTERRE"}],"92882":[{"city":"NANTERRE CEDEX 9","zipcode_valid":"92000","city_valid":"NANTERRE"}],"92883":[{"city":"NANTERRE CEDEX 9","zipcode_valid":"92000","city_valid":"NANTERRE"}],"92884":[{"city":"NANTERRE CEDEX 9","zipcode_valid":"92000","city_valid":"NANTERRE"}],"92885":[{"city":"NANTERRE CEDEX 9","zipcode_valid":"92000","city_valid":"NANTERRE"}],"92886":[{"city":"NANTERRE CEDEX 9","zipcode_valid":"92000","city_valid":"NANTERRE"}],"92887":[{"city":"NANTERRE CEDEX 9","zipcode_valid":"92000","city_valid":"NANTERRE"}],"92889":[{"city":"NANTERRE CEDEX 9","zipcode_valid":"92000","city_valid":"NANTERRE"}],"92891":[{"city":"NANTERRE CEDEX 9","zipcode_valid":"92000","city_valid":"NANTERRE"}],"92892":[{"city":"NANTERRE CEDEX 9","zipcode_valid":"92000","city_valid":"NANTERRE"}],"92893":[{"city":"NANTERRE CEDEX 9","zipcode_valid":"92000","city_valid":"NANTERRE"}],"92894":[{"city":"NANTERRE CEDEX 9","zipcode_valid":"92000","city_valid":"NANTERRE"}],"92895":[{"city":"NANTERRE CEDEX 9","zipcode_valid":"92000","city_valid":"NANTERRE"}],"92896":[{"city":"NANTERRE CEDEX 9","zipcode_valid":"92000","city_valid":"NANTERRE"}],"92897":[{"city":"NANTERRE CEDEX 9","zipcode_valid":"92000","city_valid":"NANTERRE"}],"92898":[{"city":"NANTERRE CEDEX 9","zipcode_valid":"92000","city_valid":"NANTERRE"}],"92899":[{"city":"NANTERRE CEDEX 9","zipcode_valid":"92000","city_valid":"NANTERRE"}],"92901":[{"city":"PARIS LA DEFENSE CEDEX","zipcode_valid":"92400","city_valid":"COURBEVOIE"}],"92902":[{"city":"PARIS LA DEFENSE CEDEX","zipcode_valid":"92400","city_valid":"COURBEVOIE"}],"92903":[{"city":"PARIS LA DEFENSE CEDEX","zipcode_valid":"92999","city_valid":"PARIS LA DEFENSE"}],"92904":[{"city":"PARIS LA DEFENSE CEDEX","zipcode_valid":"92800","city_valid":"PUTEAUX"}],"92905":[{"city":"PARIS LA DEFENSE CEDEX","zipcode_valid":"92999","city_valid":"PARIS LA DEFENSE"}],"92906":[{"city":"PARIS LA DEFENSE CEDEX","zipcode_valid":"92800","city_valid":"PUTEAUX"}],"92907":[{"city":"PARIS LA DEFENSE CEDEX","zipcode_valid":"92800","city_valid":"PUTEAUX"}],"92908":[{"city":"PARIS LA DEFENSE CEDEX","zipcode_valid":"92800","city_valid":"PUTEAUX"}],"92909":[{"city":"PARIS LA DEFENSE CEDEX","zipcode_valid":"92800","city_valid":"PUTEAUX"}],"92910":[{"city":"PARIS LA DEFENSE CEDEX","zipcode_valid":"92999","city_valid":"PARIS LA DEFENSE"}],"92911":[{"city":"PARIS LA DEFENSE CEDEX","zipcode_valid":"92800","city_valid":"PUTEAUX"}],"92912":[{"city":"PARIS LA DEFENSE CEDEX","zipcode_valid":"92999","city_valid":"PARIS LA DEFENSE"}],"92913":[{"city":"PARIS LA DEFENSE CEDEX","zipcode_valid":"92400","city_valid":"COURBEVOIE"}],"92914":[{"city":"PARIS LA DEFENSE CEDEX","zipcode_valid":"92800","city_valid":"PUTEAUX"}],"92915":[{"city":"PARIS LA DEFENSE CEDEX","zipcode_valid":"92800","city_valid":"PUTEAUX"}],"92916":[{"city":"PARIS LA DEFENSE CEDEX","zipcode_valid":"92400","city_valid":"COURBEVOIE"}],"92917":[{"city":"PARIS LA DEFENSE CEDEX","zipcode_valid":"92999","city_valid":"PARIS LA DEFENSE"}],"92918":[{"city":"PARIS LA DEFENSE CEDEX","zipcode_valid":"92999","city_valid":"PARIS LA DEFENSE"}],"92919":[{"city":"PARIS LA DEFENSE CEDEX","zipcode_valid":"92800","city_valid":"PUTEAUX"}],"92920":[{"city":"PARIS LA DEFENSE CEDEX","zipcode_valid":"92400","city_valid":"COURBEVOIE"}],"92921":[{"city":"PARIS LA DEFENSE CEDEX","zipcode_valid":"92800","city_valid":"PUTEAUX"}],"92922":[{"city":"PARIS LA DEFENSE CEDEX","zipcode_valid":"92999","city_valid":"PARIS LA DEFENSE"}],"92923":[{"city":"PARIS LA DEFENSE CEDEX","zipcode_valid":"92800","city_valid":"PUTEAUX"}],"92924":[{"city":"PARIS LA DEFENSE CEDEX","zipcode_valid":"92400","city_valid":"COURBEVOIE"}],"92925":[{"city":"PARIS LA DEFENSE CEDEX","zipcode_valid":"92999","city_valid":"PARIS LA DEFENSE"}],"92926":[{"city":"PARIS LA DEFENSE CEDEX","zipcode_valid":"92400","city_valid":"COURBEVOIE"}],"92927":[{"city":"PARIS LA DEFENSE CEDEX","zipcode_valid":"92400","city_valid":"COURBEVOIE"}],"92928":[{"city":"PARIS LA DEFENSE CEDEX","zipcode_valid":"92400","city_valid":"COURBEVOIE"}],"92929":[{"city":"PARIS LA DEFENSE CEDEX","zipcode_valid":"92400","city_valid":"COURBEVOIE"}],"92930":[{"city":"PARIS LA DEFENSE CEDEX","zipcode_valid":"92400","city_valid":"COURBEVOIE"}],"92931":[{"city":"PARIS LA DEFENSE CEDEX","zipcode_valid":"92400","city_valid":"COURBEVOIE"}],"92932":[{"city":"PARIS LA DEFENSE CEDEX","zipcode_valid":"92400","city_valid":"COURBEVOIE"}],"92933":[{"city":"PARIS LA DEFENSE CEDEX","zipcode_valid":"92400","city_valid":"COURBEVOIE"}],"92934":[{"city":"PARIS LA DEFENSE CEDEX","zipcode_valid":"92400","city_valid":"COURBEVOIE"}],"92935":[{"city":"PARIS LA DEFENSE CEDEX","zipcode_valid":"92999","city_valid":"PARIS LA DEFENSE"}],"92936":[{"city":"PARIS LA DEFENSE CEDEX","zipcode_valid":"92800","city_valid":"PUTEAUX"}],"92937":[{"city":"PARIS LA DEFENSE CEDEX","zipcode_valid":"92800","city_valid":"PUTEAUX"}],"92938":[{"city":"PARIS LA DEFENSE CEDEX","zipcode_valid":"92999","city_valid":"PARIS LA DEFENSE"}],"92939":[{"city":"PARIS LA DEFENSE CEDEX","zipcode_valid":"92800","city_valid":"PUTEAUX"}],"92952":[{"city":"LA GARENNE COLOMBES CEDEX","zipcode_valid":"92250","city_valid":"LA GARENNE COLOMBES"}],"92959":[{"city":"LA GARENNE COLOMBES CEDEX","zipcode_valid":"92250","city_valid":"LA GARENNE COLOMBES"}],"92970":[{"city":"PARIS LA DEFENSE CEDEX","zipcode_valid":"92800","city_valid":"PUTEAUX"}],"92971":[{"city":"PARIS LA DEFENSE CEDEX","zipcode_valid":"92400","city_valid":"COURBEVOIE"}],"92972":[{"city":"PARIS LA DEFENSE CEDEX","zipcode_valid":"92800","city_valid":"PUTEAUX"}],"92973":[{"city":"PARIS LA DEFENSE CEDEX","zipcode_valid":"92400","city_valid":"COURBEVOIE"}],"92974":[{"city":"PARIS LA DEFENSE CEDEX","zipcode_valid":"92999","city_valid":"PARIS LA DEFENSE"}],"92975":[{"city":"PARIS LA DEFENSE CEDEX","zipcode_valid":"92400","city_valid":"COURBEVOIE"}],"92976":[{"city":"PARIS LA DEFENSE CEDEX","zipcode_valid":"92999","city_valid":"PARIS LA DEFENSE"}],"92977":[{"city":"PARIS LA DEFENSE CEDEX","zipcode_valid":"92800","city_valid":"PUTEAUX"}],"92978":[{"city":"PARIS LA DEFENSE CEDEX","zipcode_valid":"92400","city_valid":"COURBEVOIE"}],"92979":[{"city":"PARIS LA DEFENSE CEDEX","zipcode_valid":"92400","city_valid":"COURBEVOIE"}],"92980":[{"city":"PARIS LA DEFENSE CEDEX","zipcode_valid":"92800","city_valid":"PUTEAUX"}],"92981":[{"city":"PARIS LA DEFENSE CEDEX","zipcode_valid":"92800","city_valid":"PUTEAUX"}],"92982":[{"city":"PARIS LA DEFENSE CEDEX","zipcode_valid":"92999","city_valid":"PARIS LA DEFENSE"}],"92983":[{"city":"PARIS LA DEFENSE CEDEX","zipcode_valid":"92999","city_valid":"PARIS LA DEFENSE"}],"92984":[{"city":"PARIS LA DEFENSE CEDEX","zipcode_valid":"92999","city_valid":"PARIS LA DEFENSE"}],"92985":[{"city":"PARIS LA DEFENSE CEDEX","zipcode_valid":"92000","city_valid":"NANTERRE"}],"92986":[{"city":"PARIS LA DEFENSE CEDEX","zipcode_valid":"92800","city_valid":"PUTEAUX"}],"92987":[{"city":"PARIS LA DEFENSE CEDEX","zipcode_valid":"92800","city_valid":"PUTEAUX"}],"92988":[{"city":"PARIS LA DEFENSE CEDEX","zipcode_valid":"92800","city_valid":"PUTEAUX"}],"92989":[{"city":"PARIS LA DEFENSE CEDEX","zipcode_valid":"92400","city_valid":"COURBEVOIE"}],"92999":[{"city":"PARIS LA DEFENSE CEDEX","zipcode_valid":"92000","city_valid":"NANTERRE"}]}